[{"data":{"id":"AppVeyor","source":null,"target":null}},{"data":{"id":"d57dcb0b-8ae7-43fd-b9c4-30bd7edbd34b","source":"AppVeyor","target":"Upload-AppVeyor-Artifacts"}},{"data":{"id":"7893d499-9617-42ad-9979-fd7c8f0c9426","source":"AppVeyor","target":"Publish-MyGet-Packages"}},{"data":{"id":"c58d6325-0f21-45db-84f4-74c71969c2f2","source":"AppVeyor","target":"Publish-Nuget-Packages"}},{"data":{"id":"74526890-2c2c-40ed-b138-f237cb8be16e","source":"AppVeyor","target":"Publish-GitHub-Release"}},{"data":{"id":"e3bd5252-fbb8-429e-a6a7-b30a875ee523","source":"AppVeyor","target":"Publish-Documentation"}},{"data":{"id":"Publish-Documentation","source":null,"target":null}},{"data":{"id":"27629f20-bfdd-400d-8aab-a422bf949812","source":"Publish-Documentation","target":"Clean-Documentation"}},{"data":{"id":"6ed00f7a-4bac-4c0f-8875-79e8518df15b","source":"Publish-Documentation","target":"Deploy-Graph-Documentation"}},{"data":{"id":"Deploy-Graph-Documentation","source":null,"target":null}},{"data":{"id":"Clean-Documentation","source":null,"target":null}},{"data":{"id":"Publish-GitHub-Release","source":null,"target":null}},{"data":{"id":"63f52dc2-adf4-46b1-8188-f869d3a72bf7","source":"Publish-GitHub-Release","target":"Package"}},{"data":{"id":"Package","source":null,"target":null}},{"data":{"id":"01f08a95-0d3f-4238-9a31-d8c3a7be55b1","source":"Package","target":"Export-Release-Notes"}},{"data":{"id":"ef8cefb1-9933-4812-90f6-a254f9932b60","source":"Package","target":"Create-Nuget-Package"}},{"data":{"id":"Create-Nuget-Package","source":null,"target":null}},{"data":{"id":"1a5b7aea-30d8-4594-a147-0f78547cc786","source":"Create-Nuget-Package","target":"Clean"}},{"data":{"id":"Clean","source":null,"target":null}},{"data":{"id":"a0d86314-7cb9-4c96-acc1-0061341abee2","source":"Clean","target":"Show-Info"}},{"data":{"id":"b5c05258-8490-43b0-a4d8-9b7e8783258c","source":"Clean","target":"Print-AppVeyor-Environment-Variables"}},{"data":{"id":"Print-AppVeyor-Environment-Variables","source":null,"target":null}},{"data":{"id":"Show-Info","source":null,"target":null}},{"data":{"id":"Export-Release-Notes","source":null,"target":null}},{"data":{"id":"Publish-Nuget-Packages","source":null,"target":null}},{"data":{"id":"e2b74f97-9444-4063-b249-748882a6d0c1","source":"Publish-Nuget-Packages","target":"Package"}},{"data":{"id":"Package","source":null,"target":null}},{"data":{"id":"5b44eaae-12ed-47df-b616-9a8561eb25c3","source":"Package","target":"Export-Release-Notes"}},{"data":{"id":"f6129e9e-7352-4a92-b24e-edc1797c4c68","source":"Package","target":"Create-Nuget-Package"}},{"data":{"id":"Create-Nuget-Package","source":null,"target":null}},{"data":{"id":"60b724b5-948f-4538-ba23-d135986fc95f","source":"Create-Nuget-Package","target":"Clean"}},{"data":{"id":"Clean","source":null,"target":null}},{"data":{"id":"1c4b8402-853d-4c86-bec3-fad1d0813b9c","source":"Clean","target":"Show-Info"}},{"data":{"id":"bddb8551-1ca3-4b75-b02f-3d1cc31746d4","source":"Clean","target":"Print-AppVeyor-Environment-Variables"}},{"data":{"id":"Print-AppVeyor-Environment-Variables","source":null,"target":null}},{"data":{"id":"Show-Info","source":null,"target":null}},{"data":{"id":"Export-Release-Notes","source":null,"target":null}},{"data":{"id":"Publish-MyGet-Packages","source":null,"target":null}},{"data":{"id":"6cc37c8d-f3af-415c-8ffd-7ca4afd14293","source":"Publish-MyGet-Packages","target":"Package"}},{"data":{"id":"Package","source":null,"target":null}},{"data":{"id":"736f9917-f093-4ec5-9d82-cc2075260e97","source":"Package","target":"Export-Release-Notes"}},{"data":{"id":"a48df2c9-52d8-440e-932e-bc265ae9acb2","source":"Package","target":"Create-Nuget-Package"}},{"data":{"id":"Create-Nuget-Package","source":null,"target":null}},{"data":{"id":"7d93332a-d534-44be-af56-80843e03b191","source":"Create-Nuget-Package","target":"Clean"}},{"data":{"id":"Clean","source":null,"target":null}},{"data":{"id":"a0872dae-cc7f-463b-8f29-1967813899a7","source":"Clean","target":"Show-Info"}},{"data":{"id":"6c5e9cc5-1f2e-497c-a28f-58223a931971","source":"Clean","target":"Print-AppVeyor-Environment-Variables"}},{"data":{"id":"Print-AppVeyor-Environment-Variables","source":null,"target":null}},{"data":{"id":"Show-Info","source":null,"target":null}},{"data":{"id":"Export-Release-Notes","source":null,"target":null}},{"data":{"id":"Upload-AppVeyor-Artifacts","source":null,"target":null}},{"data":{"id":"31d58c7a-95ec-4c39-b5d9-986cb9b93b49","source":"Upload-AppVeyor-Artifacts","target":"Package"}},{"data":{"id":"Package","source":null,"target":null}},{"data":{"id":"a1aa8d42-9412-4808-8572-ff553a33f46b","source":"Package","target":"Export-Release-Notes"}},{"data":{"id":"81c67430-f725-4242-9cbe-d05d7bb02e30","source":"Package","target":"Create-Nuget-Package"}},{"data":{"id":"Create-Nuget-Package","source":null,"target":null}},{"data":{"id":"039b21a1-f64c-437a-a224-06ee8f34a466","source":"Create-Nuget-Package","target":"Clean"}},{"data":{"id":"Clean","source":null,"target":null}},{"data":{"id":"80da195a-fe31-4ca5-9c08-74ed87a04ebc","source":"Clean","target":"Show-Info"}},{"data":{"id":"17de6141-a6fa-429e-a1ab-ff524d75cb5a","source":"Clean","target":"Print-AppVeyor-Environment-Variables"}},{"data":{"id":"Print-AppVeyor-Environment-Variables","source":null,"target":null}},{"data":{"id":"Show-Info","source":null,"target":null}},{"data":{"id":"Export-Release-Notes","source":null,"target":null}}]