[{"data":{"id":"AppVeyor","source":null,"target":null}},{"data":{"id":"36aa229b-f6ec-403c-bb71-8ef0192bf05b","source":"AppVeyor","target":"Upload-AppVeyor-Artifacts"}},{"data":{"id":"557e3f0f-0c67-440d-a9b1-bd9147b6d007","source":"AppVeyor","target":"Publish-MyGet-Packages"}},{"data":{"id":"0c897943-ee46-43fe-a0c6-b1e18b738062","source":"AppVeyor","target":"Publish-Nuget-Packages"}},{"data":{"id":"fb6ccc78-ca31-45c2-9909-31044cb39eb6","source":"AppVeyor","target":"Publish-GitHub-Release"}},{"data":{"id":"567352b6-bf0e-4c74-87ab-e161f8c55c91","source":"AppVeyor","target":"Publish-Documentation"}},{"data":{"id":"656fe67c-9a39-4f68-bd08-f295eb612aee","source":"AppVeyor","target":"Upload-Coverage-Report"}},{"data":{"id":"28ae3140-f567-4f92-ae75-0b8fca2656e1","source":"AppVeyor","target":"Publish-Chocolatey-Packages"}},{"data":{"id":"Publish-Chocolatey-Packages","source":null,"target":null}},{"data":{"id":"4a2efa5f-b187-49ec-8271-36ef429a46a6","source":"Publish-Chocolatey-Packages","target":"Package"}},{"data":{"id":"Package","source":null,"target":null}},{"data":{"id":"ec0e2ba6-978a-44c9-93b2-0d6f40cd742f","source":"Package","target":"Export-Release-Notes"}},{"data":{"id":"809703e5-5b17-405a-95eb-1ce7ac6c31cc","source":"Package","target":"Analyze"}},{"data":{"id":"c60da842-75fc-4190-913f-9dad628642ee","source":"Package","target":"Test"}},{"data":{"id":"c77ebd5b-c1b1-4cec-a0b1-fb04a96a5111","source":"Package","target":"Create-NuGet-Packages"}},{"data":{"id":"a53fae52-73d7-4480-adcb-e629ad4dbf4b","source":"Package","target":"Create-Chocolatey-Packages"}},{"data":{"id":"Create-Chocolatey-Packages","source":null,"target":null}},{"data":{"id":"4939bd9c-6b38-4dab-9bcd-4f7f5781df41","source":"Create-Chocolatey-Packages","target":"Clean"}},{"data":{"id":"9cec9d1f-e14b-4900-8cb7-bc15d3c99896","source":"Create-Chocolatey-Packages","target":"Build"}},{"data":{"id":"Build","source":null,"target":null}},{"data":{"id":"7538b276-cf17-4070-9851-a74ee5794733","source":"Build","target":"Clean"}},{"data":{"id":"766f3e5f-37b8-4bb5-8994-211be68924c0","source":"Build","target":"Restore"}},{"data":{"id":"Restore","source":null,"target":null}},{"data":{"id":"Clean","source":null,"target":null}},{"data":{"id":"1c7bceca-11c9-45f0-87b2-b6e6dc285f9b","source":"Clean","target":"Show-Info"}},{"data":{"id":"9dbf9c17-0da3-429d-a5e6-29248b9cd7b7","source":"Clean","target":"Print-AppVeyor-Environment-Variables"}},{"data":{"id":"Print-AppVeyor-Environment-Variables","source":null,"target":null}},{"data":{"id":"Show-Info","source":null,"target":null}},{"data":{"id":"Clean","source":null,"target":null}},{"data":{"id":"bbf349bc-0729-4ab2-957c-ea1f2fe0735e","source":"Clean","target":"Show-Info"}},{"data":{"id":"96b7a06f-7824-44a5-bd8d-a176107ca2ae","source":"Clean","target":"Print-AppVeyor-Environment-Variables"}},{"data":{"id":"Print-AppVeyor-Environment-Variables","source":null,"target":null}},{"data":{"id":"Show-Info","source":null,"target":null}},{"data":{"id":"Create-NuGet-Packages","source":null,"target":null}},{"data":{"id":"c628be8f-6ff3-4529-8908-3a1cebfcb769","source":"Create-NuGet-Packages","target":"Clean"}},{"data":{"id":"2b5b3b22-171e-466c-809f-2eda9a97c552","source":"Create-NuGet-Packages","target":"Build"}},{"data":{"id":"Build","source":null,"target":null}},{"data":{"id":"456aa81f-aed7-47ca-9bd3-c61188820d20","source":"Build","target":"Clean"}},{"data":{"id":"e6283a1c-2107-4cd4-8230-20857fbb2f90","source":"Build","target":"Restore"}},{"data":{"id":"Restore","source":null,"target":null}},{"data":{"id":"Clean","source":null,"target":null}},{"data":{"id":"16cc59c0-c8bc-43ab-9b05-eedabaac5488","source":"Clean","target":"Show-Info"}},{"data":{"id":"888d854b-57d0-414b-8bcb-9546fb7a3eab","source":"Clean","target":"Print-AppVeyor-Environment-Variables"}},{"data":{"id":"Print-AppVeyor-Environment-Variables","source":null,"target":null}},{"data":{"id":"Show-Info","source":null,"target":null}},{"data":{"id":"Clean","source":null,"target":null}},{"data":{"id":"f02c86a3-c4af-4ad0-aed6-9accc6dbea82","source":"Clean","target":"Show-Info"}},{"data":{"id":"35b08edf-a2ce-44d1-8b5c-24d5204d9af6","source":"Clean","target":"Print-AppVeyor-Environment-Variables"}},{"data":{"id":"Print-AppVeyor-Environment-Variables","source":null,"target":null}},{"data":{"id":"Show-Info","source":null,"target":null}},{"data":{"id":"Test","source":null,"target":null}},{"data":{"id":"7900f24b-55bb-4b02-a00a-bca799923352","source":"Test","target":"Build"}},{"data":{"id":"81c9be52-932b-4d68-96c5-50f30871bdba","source":"Test","target":"Test-NUnit"}},{"data":{"id":"c32bebfe-a85f-4be8-b416-3b15d1e8ab9b","source":"Test","target":"Test-xUnit"}},{"data":{"id":"14bbcc52-6c34-455a-a3bb-717eb6c77c5a","source":"Test","target":"Test-MSTest"}},{"data":{"id":"fe9e3ac4-f858-441b-b661-1b438784296e","source":"Test","target":"Test-VSTest"}},{"data":{"id":"f820afef-38b9-4363-9972-3e66003b3ac7","source":"Test","target":"Test-Fixie"}},{"data":{"id":"Test-Fixie","source":null,"target":null}},{"data":{"id":"ab666053-c91e-48e2-8046-87c5c3a2cd19","source":"Test-Fixie","target":"Install-OpenCover"}},{"data":{"id":"Install-OpenCover","source":null,"target":null}},{"data":{"id":"fac18e8e-adce-4aa9-b24f-bddc9f0f9e75","source":"Install-OpenCover","target":"Install-ReportUnit"}},{"data":{"id":"Install-ReportUnit","source":null,"target":null}},{"data":{"id":"7f4134b1-8a70-4903-ab1d-aee97f5f8bd0","source":"Install-ReportUnit","target":"Install-ReportGenerator"}},{"data":{"id":"Install-ReportGenerator","source":null,"target":null}},{"data":{"id":"146c4a14-0d2b-4b74-894a-c9b365781e57","source":"Install-ReportGenerator","target":"Build"}},{"data":{"id":"Build","source":null,"target":null}},{"data":{"id":"c3757333-39a5-4ca6-9cc8-30b5c34551c8","source":"Build","target":"Clean"}},{"data":{"id":"76c5f50f-f8ab-4b63-9574-61e2ebf2bf5a","source":"Build","target":"Restore"}},{"data":{"id":"Restore","source":null,"target":null}},{"data":{"id":"Clean","source":null,"target":null}},{"data":{"id":"48224fc3-c487-4dad-9d97-0d73b860ee66","source":"Clean","target":"Show-Info"}},{"data":{"id":"d490db8d-af35-4cf6-8cdd-809d6e410ab8","source":"Clean","target":"Print-AppVeyor-Environment-Variables"}},{"data":{"id":"Print-AppVeyor-Environment-Variables","source":null,"target":null}},{"data":{"id":"Show-Info","source":null,"target":null}},{"data":{"id":"Test-VSTest","source":null,"target":null}},{"data":{"id":"44fe8ef4-9b3d-4c46-9794-1abd7e8ac47b","source":"Test-VSTest","target":"Install-OpenCover"}},{"data":{"id":"Install-OpenCover","source":null,"target":null}},{"data":{"id":"314e288f-a20c-4229-9fa2-6638400a76e4","source":"Install-OpenCover","target":"Install-ReportUnit"}},{"data":{"id":"Install-ReportUnit","source":null,"target":null}},{"data":{"id":"64f14f89-8630-4eb8-89bb-94a93b3708cb","source":"Install-ReportUnit","target":"Install-ReportGenerator"}},{"data":{"id":"Install-ReportGenerator","source":null,"target":null}},{"data":{"id":"1b83f52f-eb43-4535-ade7-ca4e253a64d4","source":"Install-ReportGenerator","target":"Build"}},{"data":{"id":"Build","source":null,"target":null}},{"data":{"id":"12a5f303-ea20-4ce2-ab60-3eab6becbfb5","source":"Build","target":"Clean"}},{"data":{"id":"ed1fa157-df7d-49c3-99af-ac60ede1e314","source":"Build","target":"Restore"}},{"data":{"id":"Restore","source":null,"target":null}},{"data":{"id":"Clean","source":null,"target":null}},{"data":{"id":"5b94c226-96b2-4a84-9286-c9b96de57e02","source":"Clean","target":"Show-Info"}},{"data":{"id":"5625afd6-417b-426f-8a0c-738e2f369101","source":"Clean","target":"Print-AppVeyor-Environment-Variables"}},{"data":{"id":"Print-AppVeyor-Environment-Variables","source":null,"target":null}},{"data":{"id":"Show-Info","source":null,"target":null}},{"data":{"id":"Test-MSTest","source":null,"target":null}},{"data":{"id":"7fbb0fec-2dd0-4c4b-8070-b91373371092","source":"Test-MSTest","target":"Install-OpenCover"}},{"data":{"id":"Install-OpenCover","source":null,"target":null}},{"data":{"id":"cb722435-b603-49bb-a575-2a06d8fd2457","source":"Install-OpenCover","target":"Install-ReportUnit"}},{"data":{"id":"Install-ReportUnit","source":null,"target":null}},{"data":{"id":"57fdb1b7-a3f2-4f46-ab4a-ce172672e89a","source":"Install-ReportUnit","target":"Install-ReportGenerator"}},{"data":{"id":"Install-ReportGenerator","source":null,"target":null}},{"data":{"id":"61c8b5be-cf51-499f-8381-aabcd16c28c7","source":"Install-ReportGenerator","target":"Build"}},{"data":{"id":"Build","source":null,"target":null}},{"data":{"id":"872d5fa8-266b-4c45-8ec6-c679b64b4107","source":"Build","target":"Clean"}},{"data":{"id":"538b7775-317b-483c-a934-c97bb178aef5","source":"Build","target":"Restore"}},{"data":{"id":"Restore","source":null,"target":null}},{"data":{"id":"Clean","source":null,"target":null}},{"data":{"id":"7f51748c-2512-4cca-a733-ad67d8ce419c","source":"Clean","target":"Show-Info"}},{"data":{"id":"eac9e957-ce7c-4f1d-9662-892dfd03765b","source":"Clean","target":"Print-AppVeyor-Environment-Variables"}},{"data":{"id":"Print-AppVeyor-Environment-Variables","source":null,"target":null}},{"data":{"id":"Show-Info","source":null,"target":null}},{"data":{"id":"Test-xUnit","source":null,"target":null}},{"data":{"id":"2c5ec2fd-6129-467f-b5f7-8539ed7ef2e2","source":"Test-xUnit","target":"Install-OpenCover"}},{"data":{"id":"Install-OpenCover","source":null,"target":null}},{"data":{"id":"1e72d6de-b1f3-476f-afc3-60c3160a0ebf","source":"Install-OpenCover","target":"Install-ReportUnit"}},{"data":{"id":"Install-ReportUnit","source":null,"target":null}},{"data":{"id":"d7135f43-5940-4a3b-b2d2-c8d80dd88e5f","source":"Install-ReportUnit","target":"Install-ReportGenerator"}},{"data":{"id":"Install-ReportGenerator","source":null,"target":null}},{"data":{"id":"b2ddf508-dcc2-4a65-9bee-44d3b2ce398b","source":"Install-ReportGenerator","target":"Build"}},{"data":{"id":"Build","source":null,"target":null}},{"data":{"id":"bf8e35e2-45ba-4d0d-9f90-17265f66fabb","source":"Build","target":"Clean"}},{"data":{"id":"cfe8ac57-a44f-4791-95b0-a6f51954cdb0","source":"Build","target":"Restore"}},{"data":{"id":"Restore","source":null,"target":null}},{"data":{"id":"Clean","source":null,"target":null}},{"data":{"id":"8cd3341e-7579-4e0e-a64a-4960ce367dda","source":"Clean","target":"Show-Info"}},{"data":{"id":"db9d04c4-ffb1-4594-8391-5c99c1f6bb33","source":"Clean","target":"Print-AppVeyor-Environment-Variables"}},{"data":{"id":"Print-AppVeyor-Environment-Variables","source":null,"target":null}},{"data":{"id":"Show-Info","source":null,"target":null}},{"data":{"id":"Test-NUnit","source":null,"target":null}},{"data":{"id":"7eb03594-6157-4d9f-a3ad-94c03fc66916","source":"Test-NUnit","target":"Install-OpenCover"}},{"data":{"id":"Install-OpenCover","source":null,"target":null}},{"data":{"id":"e4df1f38-fb00-42ab-b177-51037e0bfac1","source":"Install-OpenCover","target":"Install-ReportUnit"}},{"data":{"id":"Install-ReportUnit","source":null,"target":null}},{"data":{"id":"415527e0-92a7-44cd-aec0-bb56ad0de9d5","source":"Install-ReportUnit","target":"Install-ReportGenerator"}},{"data":{"id":"Install-ReportGenerator","source":null,"target":null}},{"data":{"id":"c7b00c7e-635c-4b23-ad3f-27f70f1b046f","source":"Install-ReportGenerator","target":"Build"}},{"data":{"id":"Build","source":null,"target":null}},{"data":{"id":"6172aa54-c44d-4880-bb8b-39bc823743a0","source":"Build","target":"Clean"}},{"data":{"id":"1f2af78b-bbc3-4f71-8635-c755b7e2023a","source":"Build","target":"Restore"}},{"data":{"id":"Restore","source":null,"target":null}},{"data":{"id":"Clean","source":null,"target":null}},{"data":{"id":"f9d73ecd-11bb-4feb-98de-35841d80dfb1","source":"Clean","target":"Show-Info"}},{"data":{"id":"1156c9e0-6d1c-47a8-a740-49d812974e0f","source":"Clean","target":"Print-AppVeyor-Environment-Variables"}},{"data":{"id":"Print-AppVeyor-Environment-Variables","source":null,"target":null}},{"data":{"id":"Show-Info","source":null,"target":null}},{"data":{"id":"Build","source":null,"target":null}},{"data":{"id":"fd76b807-1b8e-4e93-bc25-e2da9d849cf3","source":"Build","target":"Clean"}},{"data":{"id":"c87206e7-008d-4adc-bd9a-62dc904d15c2","source":"Build","target":"Restore"}},{"data":{"id":"Restore","source":null,"target":null}},{"data":{"id":"Clean","source":null,"target":null}},{"data":{"id":"6f735da0-b927-48a0-a073-dee96f1d8bf8","source":"Clean","target":"Show-Info"}},{"data":{"id":"f5db5754-a9cf-4867-ab9c-a7af47c41748","source":"Clean","target":"Print-AppVeyor-Environment-Variables"}},{"data":{"id":"Print-AppVeyor-Environment-Variables","source":null,"target":null}},{"data":{"id":"Show-Info","source":null,"target":null}},{"data":{"id":"Analyze","source":null,"target":null}},{"data":{"id":"cb13dcd0-2cbd-4c89-b361-af4e769b833d","source":"Analyze","target":"DupFinder"}},{"data":{"id":"ad65f4ce-6a86-4a57-a267-c314dd2f15ec","source":"Analyze","target":"InspectCode"}},{"data":{"id":"InspectCode","source":null,"target":null}},{"data":{"id":"01d66429-f670-4e1a-a931-7acfc7a18e13","source":"InspectCode","target":"Build"}},{"data":{"id":"Build","source":null,"target":null}},{"data":{"id":"7d84b953-e6c0-4e70-92c1-f0c0114796f3","source":"Build","target":"Clean"}},{"data":{"id":"d18de331-a9d4-4c9e-bcb1-8cfa948805ec","source":"Build","target":"Restore"}},{"data":{"id":"Restore","source":null,"target":null}},{"data":{"id":"Clean","source":null,"target":null}},{"data":{"id":"92d1b21c-1d62-4264-99f0-d0e27d64f503","source":"Clean","target":"Show-Info"}},{"data":{"id":"37f7a6c2-816c-4471-8a46-ece92e77b0ff","source":"Clean","target":"Print-AppVeyor-Environment-Variables"}},{"data":{"id":"Print-AppVeyor-Environment-Variables","source":null,"target":null}},{"data":{"id":"Show-Info","source":null,"target":null}},{"data":{"id":"DupFinder","source":null,"target":null}},{"data":{"id":"75800cee-e260-4332-8531-4f4d38047437","source":"DupFinder","target":"Build"}},{"data":{"id":"Build","source":null,"target":null}},{"data":{"id":"d31a1225-f3c9-43d9-acc4-1bb8f4e70e7d","source":"Build","target":"Clean"}},{"data":{"id":"558838f8-052a-4fda-80e4-830e600679cb","source":"Build","target":"Restore"}},{"data":{"id":"Restore","source":null,"target":null}},{"data":{"id":"Clean","source":null,"target":null}},{"data":{"id":"3768e1c5-b0fc-4548-9b50-ea9774e1b01d","source":"Clean","target":"Show-Info"}},{"data":{"id":"e0141628-bc97-41bf-8bfc-3e469eb11ed4","source":"Clean","target":"Print-AppVeyor-Environment-Variables"}},{"data":{"id":"Print-AppVeyor-Environment-Variables","source":null,"target":null}},{"data":{"id":"Show-Info","source":null,"target":null}},{"data":{"id":"Export-Release-Notes","source":null,"target":null}},{"data":{"id":"Upload-Coverage-Report","source":null,"target":null}},{"data":{"id":"7f4b470a-c281-4176-9708-2ec2925ffaf0","source":"Upload-Coverage-Report","target":"Upload-Coveralls-Report"}},{"data":{"id":"666a609a-38a4-400b-a82b-a6a17440bf38","source":"Upload-Coverage-Report","target":"Upload-Codecov-Report"}},{"data":{"id":"Upload-Codecov-Report","source":null,"target":null}},{"data":{"id":"5f10d8cc-c9d0-41e0-83d6-d211d4e0577d","source":"Upload-Codecov-Report","target":"Test"}},{"data":{"id":"Test","source":null,"target":null}},{"data":{"id":"09bbc66f-d825-4d04-9004-e7e9f4079504","source":"Test","target":"Build"}},{"data":{"id":"f85ed506-2f74-442b-a2f6-54d0a4024d69","source":"Test","target":"Test-NUnit"}},{"data":{"id":"5a68e4ec-746e-45c1-888a-b539231a7556","source":"Test","target":"Test-xUnit"}},{"data":{"id":"10bc4577-be4a-42a5-9f20-be3f08a7b09f","source":"Test","target":"Test-MSTest"}},{"data":{"id":"861bbece-f8ed-4cd9-9d72-b7715eca62a8","source":"Test","target":"Test-VSTest"}},{"data":{"id":"c5615e21-b6a6-47aa-93c3-a139ae653751","source":"Test","target":"Test-Fixie"}},{"data":{"id":"Test-Fixie","source":null,"target":null}},{"data":{"id":"b62981d6-1e07-4759-a280-cf68d36fa8fe","source":"Test-Fixie","target":"Install-OpenCover"}},{"data":{"id":"Install-OpenCover","source":null,"target":null}},{"data":{"id":"a516a8b2-6472-4425-bf47-792e55b1d32e","source":"Install-OpenCover","target":"Install-ReportUnit"}},{"data":{"id":"Install-ReportUnit","source":null,"target":null}},{"data":{"id":"a0aa1bdc-412e-4b16-8041-e559b888dcc8","source":"Install-ReportUnit","target":"Install-ReportGenerator"}},{"data":{"id":"Install-ReportGenerator","source":null,"target":null}},{"data":{"id":"92c6a395-66d7-4196-8a0d-6378c993f128","source":"Install-ReportGenerator","target":"Build"}},{"data":{"id":"Build","source":null,"target":null}},{"data":{"id":"d452e5f8-0e2d-4f58-8e95-cd97e144e3c6","source":"Build","target":"Clean"}},{"data":{"id":"f3fd1015-d35b-49da-bbca-c3d859466d44","source":"Build","target":"Restore"}},{"data":{"id":"Restore","source":null,"target":null}},{"data":{"id":"Clean","source":null,"target":null}},{"data":{"id":"77ea9def-18be-4612-9126-538a0a5216ac","source":"Clean","target":"Show-Info"}},{"data":{"id":"33977b8f-69c2-42ce-b4da-10639251e1c9","source":"Clean","target":"Print-AppVeyor-Environment-Variables"}},{"data":{"id":"Print-AppVeyor-Environment-Variables","source":null,"target":null}},{"data":{"id":"Show-Info","source":null,"target":null}},{"data":{"id":"Test-VSTest","source":null,"target":null}},{"data":{"id":"f196f3fb-bd38-48ad-9e45-79e9b5211ba4","source":"Test-VSTest","target":"Install-OpenCover"}},{"data":{"id":"Install-OpenCover","source":null,"target":null}},{"data":{"id":"c3db83b7-26cd-49d8-9531-8491e2d90a50","source":"Install-OpenCover","target":"Install-ReportUnit"}},{"data":{"id":"Install-ReportUnit","source":null,"target":null}},{"data":{"id":"1f5811a4-4ba9-4440-90a1-d192f4b9e614","source":"Install-ReportUnit","target":"Install-ReportGenerator"}},{"data":{"id":"Install-ReportGenerator","source":null,"target":null}},{"data":{"id":"40b1cc50-eaca-4056-a91d-76aa92e38bac","source":"Install-ReportGenerator","target":"Build"}},{"data":{"id":"Build","source":null,"target":null}},{"data":{"id":"dfb9ff50-c155-4233-86a5-cfcb14d92290","source":"Build","target":"Clean"}},{"data":{"id":"300710e5-3ad3-461b-9c9b-2d8eb6ae772f","source":"Build","target":"Restore"}},{"data":{"id":"Restore","source":null,"target":null}},{"data":{"id":"Clean","source":null,"target":null}},{"data":{"id":"fbf230a5-c9d7-4b29-a001-5b36def83155","source":"Clean","target":"Show-Info"}},{"data":{"id":"379af2ce-1202-4340-8e95-91ecc2bea21a","source":"Clean","target":"Print-AppVeyor-Environment-Variables"}},{"data":{"id":"Print-AppVeyor-Environment-Variables","source":null,"target":null}},{"data":{"id":"Show-Info","source":null,"target":null}},{"data":{"id":"Test-MSTest","source":null,"target":null}},{"data":{"id":"ee92d88d-31ad-48bf-b8c7-9e833a5c31d2","source":"Test-MSTest","target":"Install-OpenCover"}},{"data":{"id":"Install-OpenCover","source":null,"target":null}},{"data":{"id":"8eeda395-fd33-473b-b86c-ecbe2282664f","source":"Install-OpenCover","target":"Install-ReportUnit"}},{"data":{"id":"Install-ReportUnit","source":null,"target":null}},{"data":{"id":"160415a6-b08d-42e5-a51b-c128c8706575","source":"Install-ReportUnit","target":"Install-ReportGenerator"}},{"data":{"id":"Install-ReportGenerator","source":null,"target":null}},{"data":{"id":"ef6e11bd-73f1-47ce-8944-03eff8bc6feb","source":"Install-ReportGenerator","target":"Build"}},{"data":{"id":"Build","source":null,"target":null}},{"data":{"id":"684ca067-a430-4af3-b72e-78fc48d1d7db","source":"Build","target":"Clean"}},{"data":{"id":"73c59043-5c12-4c1b-b1ec-9213a7f93d3e","source":"Build","target":"Restore"}},{"data":{"id":"Restore","source":null,"target":null}},{"data":{"id":"Clean","source":null,"target":null}},{"data":{"id":"28619e80-433a-4544-b604-0006def27f9b","source":"Clean","target":"Show-Info"}},{"data":{"id":"f4a4444f-0247-425e-9932-a273744de7fd","source":"Clean","target":"Print-AppVeyor-Environment-Variables"}},{"data":{"id":"Print-AppVeyor-Environment-Variables","source":null,"target":null}},{"data":{"id":"Show-Info","source":null,"target":null}},{"data":{"id":"Test-xUnit","source":null,"target":null}},{"data":{"id":"3642b21f-699c-4055-90fe-da5739f898be","source":"Test-xUnit","target":"Install-OpenCover"}},{"data":{"id":"Install-OpenCover","source":null,"target":null}},{"data":{"id":"758edd54-67a9-4eed-b43e-f09715bc2fc5","source":"Install-OpenCover","target":"Install-ReportUnit"}},{"data":{"id":"Install-ReportUnit","source":null,"target":null}},{"data":{"id":"34dd4761-bb74-46a0-b258-ba56b790becd","source":"Install-ReportUnit","target":"Install-ReportGenerator"}},{"data":{"id":"Install-ReportGenerator","source":null,"target":null}},{"data":{"id":"9b8b3e45-e1d7-4b0d-823f-1e5035515887","source":"Install-ReportGenerator","target":"Build"}},{"data":{"id":"Build","source":null,"target":null}},{"data":{"id":"02ddf1f3-9565-4ede-8d3d-3b68d16c8eb2","source":"Build","target":"Clean"}},{"data":{"id":"c4b45c97-a41c-4c46-bb3f-d1ce14cf8f5e","source":"Build","target":"Restore"}},{"data":{"id":"Restore","source":null,"target":null}},{"data":{"id":"Clean","source":null,"target":null}},{"data":{"id":"f7b1f5e5-1622-4d89-9eb5-6e4071341c7c","source":"Clean","target":"Show-Info"}},{"data":{"id":"cf68ae90-e85c-4087-b5f6-89a3d58a1a25","source":"Clean","target":"Print-AppVeyor-Environment-Variables"}},{"data":{"id":"Print-AppVeyor-Environment-Variables","source":null,"target":null}},{"data":{"id":"Show-Info","source":null,"target":null}},{"data":{"id":"Test-NUnit","source":null,"target":null}},{"data":{"id":"3e1715d6-6300-4059-a312-47dd0131016c","source":"Test-NUnit","target":"Install-OpenCover"}},{"data":{"id":"Install-OpenCover","source":null,"target":null}},{"data":{"id":"4402a4f3-4bbd-4998-8242-a57628adeee2","source":"Install-OpenCover","target":"Install-ReportUnit"}},{"data":{"id":"Install-ReportUnit","source":null,"target":null}},{"data":{"id":"753d4718-280f-495c-b38e-8d7bc9589abf","source":"Install-ReportUnit","target":"Install-ReportGenerator"}},{"data":{"id":"Install-ReportGenerator","source":null,"target":null}},{"data":{"id":"f6240055-a195-494e-9eb8-4d4647599825","source":"Install-ReportGenerator","target":"Build"}},{"data":{"id":"Build","source":null,"target":null}},{"data":{"id":"44694a98-7a4c-45b8-b065-14b0c264f658","source":"Build","target":"Clean"}},{"data":{"id":"24dfe3d6-c83a-4ac3-98cc-2c0493cc3aa1","source":"Build","target":"Restore"}},{"data":{"id":"Restore","source":null,"target":null}},{"data":{"id":"Clean","source":null,"target":null}},{"data":{"id":"7958efa2-e864-4a15-a6b1-074b8987b4a0","source":"Clean","target":"Show-Info"}},{"data":{"id":"f20bad9a-b9cf-4d95-ab1a-46661ba05202","source":"Clean","target":"Print-AppVeyor-Environment-Variables"}},{"data":{"id":"Print-AppVeyor-Environment-Variables","source":null,"target":null}},{"data":{"id":"Show-Info","source":null,"target":null}},{"data":{"id":"Build","source":null,"target":null}},{"data":{"id":"4157da92-ed4c-44f7-b39c-76dd4690d72e","source":"Build","target":"Clean"}},{"data":{"id":"c2c3f544-15b7-4884-8a8f-a38dff058f29","source":"Build","target":"Restore"}},{"data":{"id":"Restore","source":null,"target":null}},{"data":{"id":"Clean","source":null,"target":null}},{"data":{"id":"62712705-e1e1-41a2-a4f1-0c4059ddfe97","source":"Clean","target":"Show-Info"}},{"data":{"id":"38880270-893c-4d7d-a9e2-efb846522752","source":"Clean","target":"Print-AppVeyor-Environment-Variables"}},{"data":{"id":"Print-AppVeyor-Environment-Variables","source":null,"target":null}},{"data":{"id":"Show-Info","source":null,"target":null}},{"data":{"id":"Upload-Coveralls-Report","source":null,"target":null}},{"data":{"id":"c04af8b7-b25c-4ee2-9cb0-fc31064edd6e","source":"Upload-Coveralls-Report","target":"Test"}},{"data":{"id":"Test","source":null,"target":null}},{"data":{"id":"a61e47bb-c029-42a9-bc9a-453f2fc9d36c","source":"Test","target":"Build"}},{"data":{"id":"5e341073-01a3-493d-8256-7f2c8bbdec7e","source":"Test","target":"Test-NUnit"}},{"data":{"id":"caa4cf6a-5f1e-4be8-8257-ba88e61af791","source":"Test","target":"Test-xUnit"}},{"data":{"id":"536fa51d-441d-48b5-9834-30517153a289","source":"Test","target":"Test-MSTest"}},{"data":{"id":"d26d208a-f476-4f54-b767-1094f85aab18","source":"Test","target":"Test-VSTest"}},{"data":{"id":"ec78ab34-855f-45a4-9471-dd9662876871","source":"Test","target":"Test-Fixie"}},{"data":{"id":"Test-Fixie","source":null,"target":null}},{"data":{"id":"f00453c6-0040-48c4-983d-47455cc9e058","source":"Test-Fixie","target":"Install-OpenCover"}},{"data":{"id":"Install-OpenCover","source":null,"target":null}},{"data":{"id":"5326bb16-d720-4165-89bd-1321cb300ac7","source":"Install-OpenCover","target":"Install-ReportUnit"}},{"data":{"id":"Install-ReportUnit","source":null,"target":null}},{"data":{"id":"f599542f-c3aa-4dc9-bfaf-53a4aad61f40","source":"Install-ReportUnit","target":"Install-ReportGenerator"}},{"data":{"id":"Install-ReportGenerator","source":null,"target":null}},{"data":{"id":"7a0d06fe-dd4c-4208-ad8d-2d1c7b2758ce","source":"Install-ReportGenerator","target":"Build"}},{"data":{"id":"Build","source":null,"target":null}},{"data":{"id":"9022eea1-9ca3-4130-9ccb-35ab9b8b7838","source":"Build","target":"Clean"}},{"data":{"id":"bfce9df2-bbce-4317-afdc-e4abed578322","source":"Build","target":"Restore"}},{"data":{"id":"Restore","source":null,"target":null}},{"data":{"id":"Clean","source":null,"target":null}},{"data":{"id":"bd693026-9ab6-403a-9bac-f9eddb51b752","source":"Clean","target":"Show-Info"}},{"data":{"id":"f8d1fb3a-8b40-4ffb-8fed-568fc4a7723f","source":"Clean","target":"Print-AppVeyor-Environment-Variables"}},{"data":{"id":"Print-AppVeyor-Environment-Variables","source":null,"target":null}},{"data":{"id":"Show-Info","source":null,"target":null}},{"data":{"id":"Test-VSTest","source":null,"target":null}},{"data":{"id":"81fce061-b910-4a6c-9776-4652d49185af","source":"Test-VSTest","target":"Install-OpenCover"}},{"data":{"id":"Install-OpenCover","source":null,"target":null}},{"data":{"id":"c8cbbe5b-ac4c-44af-8080-bb51892fbffb","source":"Install-OpenCover","target":"Install-ReportUnit"}},{"data":{"id":"Install-ReportUnit","source":null,"target":null}},{"data":{"id":"b5739070-b304-43ff-b19b-f4a681e918d3","source":"Install-ReportUnit","target":"Install-ReportGenerator"}},{"data":{"id":"Install-ReportGenerator","source":null,"target":null}},{"data":{"id":"04e87882-c9cd-44ab-8079-729762a8b047","source":"Install-ReportGenerator","target":"Build"}},{"data":{"id":"Build","source":null,"target":null}},{"data":{"id":"d6118eb2-b6f1-400a-a04d-20cb3ebbaa00","source":"Build","target":"Clean"}},{"data":{"id":"35e5d347-ecfa-473d-9d34-1eec471c1b90","source":"Build","target":"Restore"}},{"data":{"id":"Restore","source":null,"target":null}},{"data":{"id":"Clean","source":null,"target":null}},{"data":{"id":"16929bf9-ee25-41c3-8462-11899cc2bc4f","source":"Clean","target":"Show-Info"}},{"data":{"id":"423d2629-48d6-4ed9-9b54-4022b8d5f5ca","source":"Clean","target":"Print-AppVeyor-Environment-Variables"}},{"data":{"id":"Print-AppVeyor-Environment-Variables","source":null,"target":null}},{"data":{"id":"Show-Info","source":null,"target":null}},{"data":{"id":"Test-MSTest","source":null,"target":null}},{"data":{"id":"eda444b3-c8be-41b8-949e-1ee10e42f8c1","source":"Test-MSTest","target":"Install-OpenCover"}},{"data":{"id":"Install-OpenCover","source":null,"target":null}},{"data":{"id":"9a92ffe7-d9d6-4aba-aebe-520c029ddbdc","source":"Install-OpenCover","target":"Install-ReportUnit"}},{"data":{"id":"Install-ReportUnit","source":null,"target":null}},{"data":{"id":"abfcea2d-408d-4a4e-8816-871479704809","source":"Install-ReportUnit","target":"Install-ReportGenerator"}},{"data":{"id":"Install-ReportGenerator","source":null,"target":null}},{"data":{"id":"7cc9ee4f-3bfa-423a-b578-d24e6f33c6bd","source":"Install-ReportGenerator","target":"Build"}},{"data":{"id":"Build","source":null,"target":null}},{"data":{"id":"810b8e6f-19d9-4b0f-811d-069abff08e66","source":"Build","target":"Clean"}},{"data":{"id":"abf6d3d7-712d-4b89-abb8-d9a0f17bd5a6","source":"Build","target":"Restore"}},{"data":{"id":"Restore","source":null,"target":null}},{"data":{"id":"Clean","source":null,"target":null}},{"data":{"id":"69c279ad-470c-410f-84ad-88a123846cec","source":"Clean","target":"Show-Info"}},{"data":{"id":"e7046a71-5284-498d-b445-c5ae6d2c8feb","source":"Clean","target":"Print-AppVeyor-Environment-Variables"}},{"data":{"id":"Print-AppVeyor-Environment-Variables","source":null,"target":null}},{"data":{"id":"Show-Info","source":null,"target":null}},{"data":{"id":"Test-xUnit","source":null,"target":null}},{"data":{"id":"489b436a-8d15-4006-8814-072d53679b05","source":"Test-xUnit","target":"Install-OpenCover"}},{"data":{"id":"Install-OpenCover","source":null,"target":null}},{"data":{"id":"9c164213-0cc7-46b8-95f1-1c67c438929b","source":"Install-OpenCover","target":"Install-ReportUnit"}},{"data":{"id":"Install-ReportUnit","source":null,"target":null}},{"data":{"id":"20d56aeb-f53a-4f5c-a2e6-29b4ad9e5596","source":"Install-ReportUnit","target":"Install-ReportGenerator"}},{"data":{"id":"Install-ReportGenerator","source":null,"target":null}},{"data":{"id":"d6f58975-2aaf-4a18-ae1e-b9c7ca93a449","source":"Install-ReportGenerator","target":"Build"}},{"data":{"id":"Build","source":null,"target":null}},{"data":{"id":"f810e628-e405-45cc-b3a8-f375896468fc","source":"Build","target":"Clean"}},{"data":{"id":"87d5df06-68b8-4b5e-ae5e-0a5d3c691dc6","source":"Build","target":"Restore"}},{"data":{"id":"Restore","source":null,"target":null}},{"data":{"id":"Clean","source":null,"target":null}},{"data":{"id":"62df4d4b-a973-4ae9-8a67-87845b6315e8","source":"Clean","target":"Show-Info"}},{"data":{"id":"83371d91-106b-4132-b667-a320018c6fb2","source":"Clean","target":"Print-AppVeyor-Environment-Variables"}},{"data":{"id":"Print-AppVeyor-Environment-Variables","source":null,"target":null}},{"data":{"id":"Show-Info","source":null,"target":null}},{"data":{"id":"Test-NUnit","source":null,"target":null}},{"data":{"id":"5d06f924-1d6c-41a0-b5cd-fbfd3f210bee","source":"Test-NUnit","target":"Install-OpenCover"}},{"data":{"id":"Install-OpenCover","source":null,"target":null}},{"data":{"id":"213d4630-795d-45e7-a616-5505274a8504","source":"Install-OpenCover","target":"Install-ReportUnit"}},{"data":{"id":"Install-ReportUnit","source":null,"target":null}},{"data":{"id":"5d83d91a-80c4-4cfd-b61f-4bac1ded227b","source":"Install-ReportUnit","target":"Install-ReportGenerator"}},{"data":{"id":"Install-ReportGenerator","source":null,"target":null}},{"data":{"id":"b88ae372-82d5-416a-a341-f908b784d8c9","source":"Install-ReportGenerator","target":"Build"}},{"data":{"id":"Build","source":null,"target":null}},{"data":{"id":"226c19f4-411d-41b7-b74b-c7cb70d94b7c","source":"Build","target":"Clean"}},{"data":{"id":"b3207e35-6bfb-470f-8e18-0f600e8608f0","source":"Build","target":"Restore"}},{"data":{"id":"Restore","source":null,"target":null}},{"data":{"id":"Clean","source":null,"target":null}},{"data":{"id":"077f6aab-a4be-4f5e-9bd4-72b8643c41fe","source":"Clean","target":"Show-Info"}},{"data":{"id":"a27b2f14-a3b2-4122-b518-ad7623605feb","source":"Clean","target":"Print-AppVeyor-Environment-Variables"}},{"data":{"id":"Print-AppVeyor-Environment-Variables","source":null,"target":null}},{"data":{"id":"Show-Info","source":null,"target":null}},{"data":{"id":"Build","source":null,"target":null}},{"data":{"id":"33374ce1-f040-4dd0-bfcc-1e4a5288e216","source":"Build","target":"Clean"}},{"data":{"id":"0161a567-054a-408e-a7bc-2d891da6ddf3","source":"Build","target":"Restore"}},{"data":{"id":"Restore","source":null,"target":null}},{"data":{"id":"Clean","source":null,"target":null}},{"data":{"id":"3b5b7d10-6158-4df4-bf0d-1c1633bb139d","source":"Clean","target":"Show-Info"}},{"data":{"id":"e4acb3f7-c231-44d7-bec0-990b49dfa9b7","source":"Clean","target":"Print-AppVeyor-Environment-Variables"}},{"data":{"id":"Print-AppVeyor-Environment-Variables","source":null,"target":null}},{"data":{"id":"Show-Info","source":null,"target":null}},{"data":{"id":"Publish-Documentation","source":null,"target":null}},{"data":{"id":"57913672-e5ba-4927-952b-e3a6e6b64a9a","source":"Publish-Documentation","target":"Clean-Documentation"}},{"data":{"id":"52aae212-c362-42aa-b14f-a16eb536021c","source":"Publish-Documentation","target":"Deploy-Graph-Documentation"}},{"data":{"id":"Deploy-Graph-Documentation","source":null,"target":null}},{"data":{"id":"Clean-Documentation","source":null,"target":null}},{"data":{"id":"Publish-GitHub-Release","source":null,"target":null}},{"data":{"id":"93c32d36-be25-497e-8d6a-fb61aa76bbf0","source":"Publish-GitHub-Release","target":"Package"}},{"data":{"id":"Package","source":null,"target":null}},{"data":{"id":"7a263883-0665-4cbe-becb-9e260592e296","source":"Package","target":"Export-Release-Notes"}},{"data":{"id":"226fc17d-4078-4799-883a-ff025ec71190","source":"Package","target":"Analyze"}},{"data":{"id":"3d4de59c-df01-4e89-b66a-6a099ed3078f","source":"Package","target":"Test"}},{"data":{"id":"bc3b155a-be53-494b-8ba5-2ffb112bf78c","source":"Package","target":"Create-NuGet-Packages"}},{"data":{"id":"56d12029-00d2-4e26-b798-3f8cbe133165","source":"Package","target":"Create-Chocolatey-Packages"}},{"data":{"id":"Create-Chocolatey-Packages","source":null,"target":null}},{"data":{"id":"5aca46a2-12c5-4971-b2b0-ba165086e4d1","source":"Create-Chocolatey-Packages","target":"Clean"}},{"data":{"id":"221b9fd1-bd19-4088-998e-721a4ccc6b00","source":"Create-Chocolatey-Packages","target":"Build"}},{"data":{"id":"Build","source":null,"target":null}},{"data":{"id":"8249bbe8-e05e-44f5-b0f6-acdb495ca67c","source":"Build","target":"Clean"}},{"data":{"id":"ac2fecf0-b62e-4c1f-b47f-4641d6570d2e","source":"Build","target":"Restore"}},{"data":{"id":"Restore","source":null,"target":null}},{"data":{"id":"Clean","source":null,"target":null}},{"data":{"id":"bc06bb5a-40a2-48a3-8080-369ce2141a58","source":"Clean","target":"Show-Info"}},{"data":{"id":"43e96bbd-57e7-4f8f-9bdf-d01d26f3c3cb","source":"Clean","target":"Print-AppVeyor-Environment-Variables"}},{"data":{"id":"Print-AppVeyor-Environment-Variables","source":null,"target":null}},{"data":{"id":"Show-Info","source":null,"target":null}},{"data":{"id":"Clean","source":null,"target":null}},{"data":{"id":"ed25ac0e-a1ab-482c-9100-f94efb8d2bd8","source":"Clean","target":"Show-Info"}},{"data":{"id":"9a71296e-5a50-4c67-b3d8-1992fca6f7ae","source":"Clean","target":"Print-AppVeyor-Environment-Variables"}},{"data":{"id":"Print-AppVeyor-Environment-Variables","source":null,"target":null}},{"data":{"id":"Show-Info","source":null,"target":null}},{"data":{"id":"Create-NuGet-Packages","source":null,"target":null}},{"data":{"id":"624bf684-1c91-4d44-b411-2b39449fbbb4","source":"Create-NuGet-Packages","target":"Clean"}},{"data":{"id":"8aea2e09-021d-4454-a7a2-732c56998fec","source":"Create-NuGet-Packages","target":"Build"}},{"data":{"id":"Build","source":null,"target":null}},{"data":{"id":"f7a3d368-d7fa-4759-b7a6-bae1860533b9","source":"Build","target":"Clean"}},{"data":{"id":"5c19ecaa-17e8-40df-ba15-00e29d71ca3a","source":"Build","target":"Restore"}},{"data":{"id":"Restore","source":null,"target":null}},{"data":{"id":"Clean","source":null,"target":null}},{"data":{"id":"41d82d87-9d3b-4185-9e87-3810ec5d4645","source":"Clean","target":"Show-Info"}},{"data":{"id":"1c4f53ba-486d-4458-a0bd-5effa8d6e742","source":"Clean","target":"Print-AppVeyor-Environment-Variables"}},{"data":{"id":"Print-AppVeyor-Environment-Variables","source":null,"target":null}},{"data":{"id":"Show-Info","source":null,"target":null}},{"data":{"id":"Clean","source":null,"target":null}},{"data":{"id":"ed45b829-f360-428c-b9f6-4407fdbcecbb","source":"Clean","target":"Show-Info"}},{"data":{"id":"ccac4ace-e7a1-4a1a-9161-82a5ef9e5e2c","source":"Clean","target":"Print-AppVeyor-Environment-Variables"}},{"data":{"id":"Print-AppVeyor-Environment-Variables","source":null,"target":null}},{"data":{"id":"Show-Info","source":null,"target":null}},{"data":{"id":"Test","source":null,"target":null}},{"data":{"id":"1aecc539-7547-4e8d-b2ed-3a58afe4c343","source":"Test","target":"Build"}},{"data":{"id":"a88e2119-1d0b-4f99-a056-38f363a3a3d0","source":"Test","target":"Test-NUnit"}},{"data":{"id":"7d76e345-2fe7-451d-86c2-3f6c8d1effbf","source":"Test","target":"Test-xUnit"}},{"data":{"id":"0d77e974-e7f5-412e-923f-6d4696b25bb8","source":"Test","target":"Test-MSTest"}},{"data":{"id":"d010c9a9-6b43-48de-ac0d-814ffe0c6bd3","source":"Test","target":"Test-VSTest"}},{"data":{"id":"f5cac7ed-c4c0-4c6e-83da-c3f1b9d386c3","source":"Test","target":"Test-Fixie"}},{"data":{"id":"Test-Fixie","source":null,"target":null}},{"data":{"id":"c787da11-7403-4060-af44-70c4823c8b9f","source":"Test-Fixie","target":"Install-OpenCover"}},{"data":{"id":"Install-OpenCover","source":null,"target":null}},{"data":{"id":"868094d9-5fdf-4df4-b4c5-a9293edcebe8","source":"Install-OpenCover","target":"Install-ReportUnit"}},{"data":{"id":"Install-ReportUnit","source":null,"target":null}},{"data":{"id":"e1414ad2-9751-4528-8775-bf2b6b4dbcd0","source":"Install-ReportUnit","target":"Install-ReportGenerator"}},{"data":{"id":"Install-ReportGenerator","source":null,"target":null}},{"data":{"id":"ff0942cd-e21e-497f-86ba-37eb7acbc489","source":"Install-ReportGenerator","target":"Build"}},{"data":{"id":"Build","source":null,"target":null}},{"data":{"id":"a5d8a2d4-02c9-4796-9e24-04fe40d9c119","source":"Build","target":"Clean"}},{"data":{"id":"365f6cc7-5775-4e03-97e6-2f2eba520d29","source":"Build","target":"Restore"}},{"data":{"id":"Restore","source":null,"target":null}},{"data":{"id":"Clean","source":null,"target":null}},{"data":{"id":"419c8bc3-19ad-4c01-a0d5-c6f6d8904386","source":"Clean","target":"Show-Info"}},{"data":{"id":"6c5cecf4-0b23-47ff-ab3e-9b0feb12f673","source":"Clean","target":"Print-AppVeyor-Environment-Variables"}},{"data":{"id":"Print-AppVeyor-Environment-Variables","source":null,"target":null}},{"data":{"id":"Show-Info","source":null,"target":null}},{"data":{"id":"Test-VSTest","source":null,"target":null}},{"data":{"id":"746c076e-1069-41e4-b4e7-4b258e994f46","source":"Test-VSTest","target":"Install-OpenCover"}},{"data":{"id":"Install-OpenCover","source":null,"target":null}},{"data":{"id":"5a18973e-4a22-4899-a9cd-ce0fdd9d48b3","source":"Install-OpenCover","target":"Install-ReportUnit"}},{"data":{"id":"Install-ReportUnit","source":null,"target":null}},{"data":{"id":"04adc8bd-1f46-48fc-8627-716113d83bbe","source":"Install-ReportUnit","target":"Install-ReportGenerator"}},{"data":{"id":"Install-ReportGenerator","source":null,"target":null}},{"data":{"id":"7af28e35-4953-461a-835a-9e73e0b02063","source":"Install-ReportGenerator","target":"Build"}},{"data":{"id":"Build","source":null,"target":null}},{"data":{"id":"0c83956e-af00-4816-bf1c-c9cef70a6349","source":"Build","target":"Clean"}},{"data":{"id":"5e834432-64d2-441b-84cf-35457b04ef81","source":"Build","target":"Restore"}},{"data":{"id":"Restore","source":null,"target":null}},{"data":{"id":"Clean","source":null,"target":null}},{"data":{"id":"146406a0-5679-4c43-acc6-4edb5504f79e","source":"Clean","target":"Show-Info"}},{"data":{"id":"e3da7e06-f190-4edc-933d-5176fb6cf7d6","source":"Clean","target":"Print-AppVeyor-Environment-Variables"}},{"data":{"id":"Print-AppVeyor-Environment-Variables","source":null,"target":null}},{"data":{"id":"Show-Info","source":null,"target":null}},{"data":{"id":"Test-MSTest","source":null,"target":null}},{"data":{"id":"ca0ae0fa-0cce-45a0-b56c-d6db4f622f46","source":"Test-MSTest","target":"Install-OpenCover"}},{"data":{"id":"Install-OpenCover","source":null,"target":null}},{"data":{"id":"f6f3213f-95f7-4222-a5e0-c84da94e1014","source":"Install-OpenCover","target":"Install-ReportUnit"}},{"data":{"id":"Install-ReportUnit","source":null,"target":null}},{"data":{"id":"59c13179-cdf8-4d9a-94a7-97fb4ff4ba8c","source":"Install-ReportUnit","target":"Install-ReportGenerator"}},{"data":{"id":"Install-ReportGenerator","source":null,"target":null}},{"data":{"id":"7e7dd021-241b-4d79-90ee-6f85017af44a","source":"Install-ReportGenerator","target":"Build"}},{"data":{"id":"Build","source":null,"target":null}},{"data":{"id":"5a4a6f3a-9e3d-47a4-80b6-5e9420a65760","source":"Build","target":"Clean"}},{"data":{"id":"0e6cfa06-8479-46d6-8ca2-bdaddc8cc353","source":"Build","target":"Restore"}},{"data":{"id":"Restore","source":null,"target":null}},{"data":{"id":"Clean","source":null,"target":null}},{"data":{"id":"75613f24-22cb-4154-b1ff-b17a2d970347","source":"Clean","target":"Show-Info"}},{"data":{"id":"9225ba40-0b76-4ffd-befe-1da746ec3dfc","source":"Clean","target":"Print-AppVeyor-Environment-Variables"}},{"data":{"id":"Print-AppVeyor-Environment-Variables","source":null,"target":null}},{"data":{"id":"Show-Info","source":null,"target":null}},{"data":{"id":"Test-xUnit","source":null,"target":null}},{"data":{"id":"8fef2a2c-793c-4fbe-b75f-2b0e132dc4c2","source":"Test-xUnit","target":"Install-OpenCover"}},{"data":{"id":"Install-OpenCover","source":null,"target":null}},{"data":{"id":"0e960b2e-94a4-4b31-8f9c-55ebf11a2cf9","source":"Install-OpenCover","target":"Install-ReportUnit"}},{"data":{"id":"Install-ReportUnit","source":null,"target":null}},{"data":{"id":"6d34e030-0060-4c45-99f9-6ca6e71a5026","source":"Install-ReportUnit","target":"Install-ReportGenerator"}},{"data":{"id":"Install-ReportGenerator","source":null,"target":null}},{"data":{"id":"7844b50e-d5d3-45d3-a31f-be6f13cf6b8d","source":"Install-ReportGenerator","target":"Build"}},{"data":{"id":"Build","source":null,"target":null}},{"data":{"id":"2a6b08f4-bdda-40cb-9e72-a6736baa8736","source":"Build","target":"Clean"}},{"data":{"id":"41d976ba-cf66-44e0-9237-4835679cee13","source":"Build","target":"Restore"}},{"data":{"id":"Restore","source":null,"target":null}},{"data":{"id":"Clean","source":null,"target":null}},{"data":{"id":"b84a2e52-89a3-4f04-bd27-d32184cd93d1","source":"Clean","target":"Show-Info"}},{"data":{"id":"c31fb6ad-2723-4cb0-9b07-6f65dc5173ee","source":"Clean","target":"Print-AppVeyor-Environment-Variables"}},{"data":{"id":"Print-AppVeyor-Environment-Variables","source":null,"target":null}},{"data":{"id":"Show-Info","source":null,"target":null}},{"data":{"id":"Test-NUnit","source":null,"target":null}},{"data":{"id":"b6ff702e-a13f-4044-a17d-30d80dc7ba86","source":"Test-NUnit","target":"Install-OpenCover"}},{"data":{"id":"Install-OpenCover","source":null,"target":null}},{"data":{"id":"d2facab5-fc3c-47be-8104-3c29d784df3d","source":"Install-OpenCover","target":"Install-ReportUnit"}},{"data":{"id":"Install-ReportUnit","source":null,"target":null}},{"data":{"id":"853bcdd0-9503-45a9-9b08-642a740a8712","source":"Install-ReportUnit","target":"Install-ReportGenerator"}},{"data":{"id":"Install-ReportGenerator","source":null,"target":null}},{"data":{"id":"aab839bc-5a85-4f38-b657-e33dcf96628b","source":"Install-ReportGenerator","target":"Build"}},{"data":{"id":"Build","source":null,"target":null}},{"data":{"id":"1de0af6f-e6f7-4f09-bbfd-46dd707c550c","source":"Build","target":"Clean"}},{"data":{"id":"25b81573-6b00-422a-b65c-6c25e9ca6d2d","source":"Build","target":"Restore"}},{"data":{"id":"Restore","source":null,"target":null}},{"data":{"id":"Clean","source":null,"target":null}},{"data":{"id":"7833a5a8-fc31-4533-b89b-14c9022103af","source":"Clean","target":"Show-Info"}},{"data":{"id":"f8740a64-e3b8-4b31-80b5-8eb182666f84","source":"Clean","target":"Print-AppVeyor-Environment-Variables"}},{"data":{"id":"Print-AppVeyor-Environment-Variables","source":null,"target":null}},{"data":{"id":"Show-Info","source":null,"target":null}},{"data":{"id":"Build","source":null,"target":null}},{"data":{"id":"9d5f04a5-fcad-45b1-b974-6d39606ef37c","source":"Build","target":"Clean"}},{"data":{"id":"b9d4e0ec-cdd6-44e0-b637-caaa331a8664","source":"Build","target":"Restore"}},{"data":{"id":"Restore","source":null,"target":null}},{"data":{"id":"Clean","source":null,"target":null}},{"data":{"id":"0d0171e5-a6d0-45a8-8192-12b194e996f5","source":"Clean","target":"Show-Info"}},{"data":{"id":"bf961845-8d9f-46b5-855f-68760ed82c8c","source":"Clean","target":"Print-AppVeyor-Environment-Variables"}},{"data":{"id":"Print-AppVeyor-Environment-Variables","source":null,"target":null}},{"data":{"id":"Show-Info","source":null,"target":null}},{"data":{"id":"Analyze","source":null,"target":null}},{"data":{"id":"13eb9e55-4065-41c8-b7b2-319b503b71e3","source":"Analyze","target":"DupFinder"}},{"data":{"id":"9bf4cd42-c0ab-4a67-80ee-2e5970595df6","source":"Analyze","target":"InspectCode"}},{"data":{"id":"InspectCode","source":null,"target":null}},{"data":{"id":"c7ad6991-b61d-4940-802c-965e86be6bae","source":"InspectCode","target":"Build"}},{"data":{"id":"Build","source":null,"target":null}},{"data":{"id":"f636cf8f-07e3-480d-a0b0-3a100344ba98","source":"Build","target":"Clean"}},{"data":{"id":"eeca250d-1c1b-4d39-93e5-665689a1d3f7","source":"Build","target":"Restore"}},{"data":{"id":"Restore","source":null,"target":null}},{"data":{"id":"Clean","source":null,"target":null}},{"data":{"id":"fb83cad5-6ca6-4c3b-9e5c-82bc76f13538","source":"Clean","target":"Show-Info"}},{"data":{"id":"094dcca4-f760-47c7-8e6f-73fb81495850","source":"Clean","target":"Print-AppVeyor-Environment-Variables"}},{"data":{"id":"Print-AppVeyor-Environment-Variables","source":null,"target":null}},{"data":{"id":"Show-Info","source":null,"target":null}},{"data":{"id":"DupFinder","source":null,"target":null}},{"data":{"id":"dfec6c98-7b39-4b8b-acd7-f9ff837366c2","source":"DupFinder","target":"Build"}},{"data":{"id":"Build","source":null,"target":null}},{"data":{"id":"d543b2ff-6c14-4bbb-a1e9-0ecfac8a50df","source":"Build","target":"Clean"}},{"data":{"id":"4eae01e4-1b5a-43aa-83be-fa24066b4a67","source":"Build","target":"Restore"}},{"data":{"id":"Restore","source":null,"target":null}},{"data":{"id":"Clean","source":null,"target":null}},{"data":{"id":"a145efe3-f1a3-4503-9a1b-a473b91bddcb","source":"Clean","target":"Show-Info"}},{"data":{"id":"43835a74-10e0-4c19-b7ef-cf303f101c62","source":"Clean","target":"Print-AppVeyor-Environment-Variables"}},{"data":{"id":"Print-AppVeyor-Environment-Variables","source":null,"target":null}},{"data":{"id":"Show-Info","source":null,"target":null}},{"data":{"id":"Export-Release-Notes","source":null,"target":null}},{"data":{"id":"Publish-Nuget-Packages","source":null,"target":null}},{"data":{"id":"a0cae3c6-4103-42b1-b3fd-bef84590cdd7","source":"Publish-Nuget-Packages","target":"Package"}},{"data":{"id":"Package","source":null,"target":null}},{"data":{"id":"00feb1b7-8014-4376-8d1f-e297a4062a31","source":"Package","target":"Export-Release-Notes"}},{"data":{"id":"dbabb8ef-555f-49e0-93e2-0c3551509e5a","source":"Package","target":"Analyze"}},{"data":{"id":"3f7f456b-d71f-4ce2-b832-3d249afdd3aa","source":"Package","target":"Test"}},{"data":{"id":"f97cd3a6-2d83-4805-8bca-0145f6959431","source":"Package","target":"Create-NuGet-Packages"}},{"data":{"id":"85f9dcc3-0dd0-4b9c-947c-a76a313591f4","source":"Package","target":"Create-Chocolatey-Packages"}},{"data":{"id":"Create-Chocolatey-Packages","source":null,"target":null}},{"data":{"id":"b18e1aec-3382-4820-8e7f-07949ebf4c12","source":"Create-Chocolatey-Packages","target":"Clean"}},{"data":{"id":"aec5df42-0e50-4825-8b19-ac60a4280f72","source":"Create-Chocolatey-Packages","target":"Build"}},{"data":{"id":"Build","source":null,"target":null}},{"data":{"id":"ea76bc69-6397-4fb6-8c70-14aca9c3ef27","source":"Build","target":"Clean"}},{"data":{"id":"feaadcda-2cfa-48c1-b058-2e9328be12d0","source":"Build","target":"Restore"}},{"data":{"id":"Restore","source":null,"target":null}},{"data":{"id":"Clean","source":null,"target":null}},{"data":{"id":"88a1b2b4-a688-4a3c-aa84-d35eafd3da25","source":"Clean","target":"Show-Info"}},{"data":{"id":"1c6180c2-a1fb-4782-9d9f-2a52987b4438","source":"Clean","target":"Print-AppVeyor-Environment-Variables"}},{"data":{"id":"Print-AppVeyor-Environment-Variables","source":null,"target":null}},{"data":{"id":"Show-Info","source":null,"target":null}},{"data":{"id":"Clean","source":null,"target":null}},{"data":{"id":"9f5d3df2-3a1a-47ca-8faf-862a659af3fd","source":"Clean","target":"Show-Info"}},{"data":{"id":"d36b57fe-7e8f-438e-9478-c31e322cc760","source":"Clean","target":"Print-AppVeyor-Environment-Variables"}},{"data":{"id":"Print-AppVeyor-Environment-Variables","source":null,"target":null}},{"data":{"id":"Show-Info","source":null,"target":null}},{"data":{"id":"Create-NuGet-Packages","source":null,"target":null}},{"data":{"id":"85513c05-3594-42a6-96e6-5fdbb6fe91a1","source":"Create-NuGet-Packages","target":"Clean"}},{"data":{"id":"0229d78f-9bf5-4552-ae21-2bd97b9ed8da","source":"Create-NuGet-Packages","target":"Build"}},{"data":{"id":"Build","source":null,"target":null}},{"data":{"id":"c5262bfa-0f42-4559-a67b-e595b11ef13b","source":"Build","target":"Clean"}},{"data":{"id":"3f0e9fee-b6aa-4178-b77e-a9528aa0f7f0","source":"Build","target":"Restore"}},{"data":{"id":"Restore","source":null,"target":null}},{"data":{"id":"Clean","source":null,"target":null}},{"data":{"id":"c0a91356-8e1d-416a-a95f-4b7bcb188a33","source":"Clean","target":"Show-Info"}},{"data":{"id":"ab64358b-d1a0-4a53-84f9-e16f0782dee0","source":"Clean","target":"Print-AppVeyor-Environment-Variables"}},{"data":{"id":"Print-AppVeyor-Environment-Variables","source":null,"target":null}},{"data":{"id":"Show-Info","source":null,"target":null}},{"data":{"id":"Clean","source":null,"target":null}},{"data":{"id":"57673881-32d2-42f5-ac18-724ce8dc705b","source":"Clean","target":"Show-Info"}},{"data":{"id":"ef837093-2686-49df-abcb-1e3eca14d640","source":"Clean","target":"Print-AppVeyor-Environment-Variables"}},{"data":{"id":"Print-AppVeyor-Environment-Variables","source":null,"target":null}},{"data":{"id":"Show-Info","source":null,"target":null}},{"data":{"id":"Test","source":null,"target":null}},{"data":{"id":"def4b9bc-e982-452f-ab0e-4d0834375d41","source":"Test","target":"Build"}},{"data":{"id":"f16a8b2a-faef-4714-b345-7169dd199ea5","source":"Test","target":"Test-NUnit"}},{"data":{"id":"6e1ec2fb-fd37-4810-a75c-1738f9e35ded","source":"Test","target":"Test-xUnit"}},{"data":{"id":"577ef86b-afc6-4761-a7a8-e512d4466673","source":"Test","target":"Test-MSTest"}},{"data":{"id":"9bf7a9c3-78af-4f52-b845-a14d631e1786","source":"Test","target":"Test-VSTest"}},{"data":{"id":"81c348a8-eb8d-4a64-b5c9-429dd878bfad","source":"Test","target":"Test-Fixie"}},{"data":{"id":"Test-Fixie","source":null,"target":null}},{"data":{"id":"0566fc46-6ef1-4aaa-83d5-5ef8b7ab7cdc","source":"Test-Fixie","target":"Install-OpenCover"}},{"data":{"id":"Install-OpenCover","source":null,"target":null}},{"data":{"id":"9c2b40fb-58c1-4768-8932-8d0b75981291","source":"Install-OpenCover","target":"Install-ReportUnit"}},{"data":{"id":"Install-ReportUnit","source":null,"target":null}},{"data":{"id":"4a8d7a48-b48b-457c-a0c8-daa26c020d94","source":"Install-ReportUnit","target":"Install-ReportGenerator"}},{"data":{"id":"Install-ReportGenerator","source":null,"target":null}},{"data":{"id":"d2bcec12-fa44-4450-a840-d9bf25124422","source":"Install-ReportGenerator","target":"Build"}},{"data":{"id":"Build","source":null,"target":null}},{"data":{"id":"521d5b66-bfc7-41c3-9e32-73c903fe4aba","source":"Build","target":"Clean"}},{"data":{"id":"fed4d75a-9a12-41cc-80d6-267bb5255d02","source":"Build","target":"Restore"}},{"data":{"id":"Restore","source":null,"target":null}},{"data":{"id":"Clean","source":null,"target":null}},{"data":{"id":"c5e5781d-2cbc-496f-91fd-0e0c301eb1c9","source":"Clean","target":"Show-Info"}},{"data":{"id":"e0a12994-08aa-414b-a3a6-363d73cf69db","source":"Clean","target":"Print-AppVeyor-Environment-Variables"}},{"data":{"id":"Print-AppVeyor-Environment-Variables","source":null,"target":null}},{"data":{"id":"Show-Info","source":null,"target":null}},{"data":{"id":"Test-VSTest","source":null,"target":null}},{"data":{"id":"c5e1819a-4845-432e-b74a-a508d983b16a","source":"Test-VSTest","target":"Install-OpenCover"}},{"data":{"id":"Install-OpenCover","source":null,"target":null}},{"data":{"id":"0b537b7b-5d77-4e62-9d94-474c7588f3db","source":"Install-OpenCover","target":"Install-ReportUnit"}},{"data":{"id":"Install-ReportUnit","source":null,"target":null}},{"data":{"id":"63b82dbb-a2d1-4d82-9d2c-464172bd64a5","source":"Install-ReportUnit","target":"Install-ReportGenerator"}},{"data":{"id":"Install-ReportGenerator","source":null,"target":null}},{"data":{"id":"05c48096-8007-4deb-aeae-6fb0a04549c0","source":"Install-ReportGenerator","target":"Build"}},{"data":{"id":"Build","source":null,"target":null}},{"data":{"id":"ee4bc0a8-75d5-4d78-bea9-4a255aa1250c","source":"Build","target":"Clean"}},{"data":{"id":"6ed17ec5-78b9-4f29-a627-58aec0b4f549","source":"Build","target":"Restore"}},{"data":{"id":"Restore","source":null,"target":null}},{"data":{"id":"Clean","source":null,"target":null}},{"data":{"id":"f2994b56-4fe2-4c1a-836d-949037535cd9","source":"Clean","target":"Show-Info"}},{"data":{"id":"527e82e0-4d53-4c10-8309-69e2b463bd0e","source":"Clean","target":"Print-AppVeyor-Environment-Variables"}},{"data":{"id":"Print-AppVeyor-Environment-Variables","source":null,"target":null}},{"data":{"id":"Show-Info","source":null,"target":null}},{"data":{"id":"Test-MSTest","source":null,"target":null}},{"data":{"id":"1469fab9-8ec3-48f2-a682-6d863f4b0000","source":"Test-MSTest","target":"Install-OpenCover"}},{"data":{"id":"Install-OpenCover","source":null,"target":null}},{"data":{"id":"cce8931c-1724-4759-9a73-ecfda1edeaf1","source":"Install-OpenCover","target":"Install-ReportUnit"}},{"data":{"id":"Install-ReportUnit","source":null,"target":null}},{"data":{"id":"152015d1-a6e0-44d1-8dbc-236e3868a46c","source":"Install-ReportUnit","target":"Install-ReportGenerator"}},{"data":{"id":"Install-ReportGenerator","source":null,"target":null}},{"data":{"id":"85c976fc-2165-41b3-917f-9bb7d669eee9","source":"Install-ReportGenerator","target":"Build"}},{"data":{"id":"Build","source":null,"target":null}},{"data":{"id":"85bdd6ba-cb37-4a6c-a9ba-2610d351e6f7","source":"Build","target":"Clean"}},{"data":{"id":"7a032600-ee36-4463-bd1b-c67589326f69","source":"Build","target":"Restore"}},{"data":{"id":"Restore","source":null,"target":null}},{"data":{"id":"Clean","source":null,"target":null}},{"data":{"id":"9e53c0b0-c9d8-4e39-9f4a-d79565c41694","source":"Clean","target":"Show-Info"}},{"data":{"id":"6c642a64-08df-4a71-85eb-876f9a9935cb","source":"Clean","target":"Print-AppVeyor-Environment-Variables"}},{"data":{"id":"Print-AppVeyor-Environment-Variables","source":null,"target":null}},{"data":{"id":"Show-Info","source":null,"target":null}},{"data":{"id":"Test-xUnit","source":null,"target":null}},{"data":{"id":"d1d05934-e451-441c-ba49-939ce5140a16","source":"Test-xUnit","target":"Install-OpenCover"}},{"data":{"id":"Install-OpenCover","source":null,"target":null}},{"data":{"id":"623a973d-7c78-4691-bb01-11d89c941e76","source":"Install-OpenCover","target":"Install-ReportUnit"}},{"data":{"id":"Install-ReportUnit","source":null,"target":null}},{"data":{"id":"e7145caf-c5a5-46df-9c48-004ceef8cd5f","source":"Install-ReportUnit","target":"Install-ReportGenerator"}},{"data":{"id":"Install-ReportGenerator","source":null,"target":null}},{"data":{"id":"68e9480a-b1e4-43d2-b663-3291a61fee35","source":"Install-ReportGenerator","target":"Build"}},{"data":{"id":"Build","source":null,"target":null}},{"data":{"id":"804a5607-6599-4748-bcfe-41fb26b56ae4","source":"Build","target":"Clean"}},{"data":{"id":"26f70d8b-238f-49df-9f2c-efdcd994cee1","source":"Build","target":"Restore"}},{"data":{"id":"Restore","source":null,"target":null}},{"data":{"id":"Clean","source":null,"target":null}},{"data":{"id":"656b9795-bb39-4698-a0fd-f44cf3123e24","source":"Clean","target":"Show-Info"}},{"data":{"id":"0b34d2fe-7b55-4464-a7e5-0349574445f9","source":"Clean","target":"Print-AppVeyor-Environment-Variables"}},{"data":{"id":"Print-AppVeyor-Environment-Variables","source":null,"target":null}},{"data":{"id":"Show-Info","source":null,"target":null}},{"data":{"id":"Test-NUnit","source":null,"target":null}},{"data":{"id":"54d771cf-50be-48e3-9a04-7ee5f91633e2","source":"Test-NUnit","target":"Install-OpenCover"}},{"data":{"id":"Install-OpenCover","source":null,"target":null}},{"data":{"id":"70292370-8b6b-4ae1-ba70-34de77508dbf","source":"Install-OpenCover","target":"Install-ReportUnit"}},{"data":{"id":"Install-ReportUnit","source":null,"target":null}},{"data":{"id":"6c5c9801-9b34-4a5d-847b-4c76aef61969","source":"Install-ReportUnit","target":"Install-ReportGenerator"}},{"data":{"id":"Install-ReportGenerator","source":null,"target":null}},{"data":{"id":"6a05f882-85ca-43b8-a898-d85156b2988c","source":"Install-ReportGenerator","target":"Build"}},{"data":{"id":"Build","source":null,"target":null}},{"data":{"id":"47584f95-82eb-42e1-a7c2-9c5231fb4197","source":"Build","target":"Clean"}},{"data":{"id":"de305ba0-162c-4e7a-9f14-303df1b2853f","source":"Build","target":"Restore"}},{"data":{"id":"Restore","source":null,"target":null}},{"data":{"id":"Clean","source":null,"target":null}},{"data":{"id":"30f39516-1dd3-4747-ab88-bfbc5df484ba","source":"Clean","target":"Show-Info"}},{"data":{"id":"9bc36793-709f-47e2-8e82-cf1d0433f20d","source":"Clean","target":"Print-AppVeyor-Environment-Variables"}},{"data":{"id":"Print-AppVeyor-Environment-Variables","source":null,"target":null}},{"data":{"id":"Show-Info","source":null,"target":null}},{"data":{"id":"Build","source":null,"target":null}},{"data":{"id":"fbb8098b-1cc0-4566-b40c-fbad1ff48dea","source":"Build","target":"Clean"}},{"data":{"id":"c585f294-18ac-4840-b0d0-b00f7be2800f","source":"Build","target":"Restore"}},{"data":{"id":"Restore","source":null,"target":null}},{"data":{"id":"Clean","source":null,"target":null}},{"data":{"id":"32c8874a-f7ea-466a-a365-24d1e9dd47af","source":"Clean","target":"Show-Info"}},{"data":{"id":"05aa9f49-1cf1-4b44-b439-0e744ae52a6d","source":"Clean","target":"Print-AppVeyor-Environment-Variables"}},{"data":{"id":"Print-AppVeyor-Environment-Variables","source":null,"target":null}},{"data":{"id":"Show-Info","source":null,"target":null}},{"data":{"id":"Analyze","source":null,"target":null}},{"data":{"id":"d8d28926-d4dc-424d-9b7d-e2c571404747","source":"Analyze","target":"DupFinder"}},{"data":{"id":"44df15f4-d2de-49d1-a03d-bb7697d2f4a4","source":"Analyze","target":"InspectCode"}},{"data":{"id":"InspectCode","source":null,"target":null}},{"data":{"id":"88417141-1da3-4f9d-8b64-25761337a5a6","source":"InspectCode","target":"Build"}},{"data":{"id":"Build","source":null,"target":null}},{"data":{"id":"eb37be99-0680-4888-98c6-5418c45e1bae","source":"Build","target":"Clean"}},{"data":{"id":"62e31464-3417-457d-b969-5e37bb1267dd","source":"Build","target":"Restore"}},{"data":{"id":"Restore","source":null,"target":null}},{"data":{"id":"Clean","source":null,"target":null}},{"data":{"id":"75fcb491-1e2d-4cb7-8f7d-4f586fe57b32","source":"Clean","target":"Show-Info"}},{"data":{"id":"5f6f6263-1e18-455b-bb81-1e49e209027b","source":"Clean","target":"Print-AppVeyor-Environment-Variables"}},{"data":{"id":"Print-AppVeyor-Environment-Variables","source":null,"target":null}},{"data":{"id":"Show-Info","source":null,"target":null}},{"data":{"id":"DupFinder","source":null,"target":null}},{"data":{"id":"4895c834-1acf-47a4-bdf9-b809a18e6cc5","source":"DupFinder","target":"Build"}},{"data":{"id":"Build","source":null,"target":null}},{"data":{"id":"e7eab5d8-5bfa-4899-866b-d56951e341a4","source":"Build","target":"Clean"}},{"data":{"id":"d58817e8-ab74-4e83-861b-4612741c1853","source":"Build","target":"Restore"}},{"data":{"id":"Restore","source":null,"target":null}},{"data":{"id":"Clean","source":null,"target":null}},{"data":{"id":"687af40b-96f9-4887-a76e-76282c9a1bd0","source":"Clean","target":"Show-Info"}},{"data":{"id":"c6a2e7ce-4078-4453-a2f0-15121445e5b4","source":"Clean","target":"Print-AppVeyor-Environment-Variables"}},{"data":{"id":"Print-AppVeyor-Environment-Variables","source":null,"target":null}},{"data":{"id":"Show-Info","source":null,"target":null}},{"data":{"id":"Export-Release-Notes","source":null,"target":null}},{"data":{"id":"Publish-MyGet-Packages","source":null,"target":null}},{"data":{"id":"682f29a2-eeb6-4bdb-acf1-70b6e357b9dd","source":"Publish-MyGet-Packages","target":"Package"}},{"data":{"id":"Package","source":null,"target":null}},{"data":{"id":"9b92a677-998b-4a70-9ae3-995d8da0b5b5","source":"Package","target":"Export-Release-Notes"}},{"data":{"id":"cdd67108-9f73-4257-b96a-5bf14fa54f58","source":"Package","target":"Analyze"}},{"data":{"id":"e3042cc8-b60d-4957-9611-b589c587765b","source":"Package","target":"Test"}},{"data":{"id":"8f9d8b15-7b76-46fe-9c7a-25197795b33c","source":"Package","target":"Create-NuGet-Packages"}},{"data":{"id":"87c2a9be-bb4c-4dcb-94f7-2120c9f37494","source":"Package","target":"Create-Chocolatey-Packages"}},{"data":{"id":"Create-Chocolatey-Packages","source":null,"target":null}},{"data":{"id":"c55316d5-fca7-4b1d-994b-89dad69e5e41","source":"Create-Chocolatey-Packages","target":"Clean"}},{"data":{"id":"18e3f854-9a76-4fd3-bfcd-125ce3cfa79a","source":"Create-Chocolatey-Packages","target":"Build"}},{"data":{"id":"Build","source":null,"target":null}},{"data":{"id":"164959b9-e71d-4873-b448-9315ce6230a7","source":"Build","target":"Clean"}},{"data":{"id":"b412ed68-4828-4e6a-955d-080f3d7ff7df","source":"Build","target":"Restore"}},{"data":{"id":"Restore","source":null,"target":null}},{"data":{"id":"Clean","source":null,"target":null}},{"data":{"id":"7532f490-2c0a-48ad-8faf-c9346431fcc9","source":"Clean","target":"Show-Info"}},{"data":{"id":"a49e79ce-a6cb-4266-92f8-95ed8448d945","source":"Clean","target":"Print-AppVeyor-Environment-Variables"}},{"data":{"id":"Print-AppVeyor-Environment-Variables","source":null,"target":null}},{"data":{"id":"Show-Info","source":null,"target":null}},{"data":{"id":"Clean","source":null,"target":null}},{"data":{"id":"fe4bd631-4dcf-4914-9bde-967a900bc9be","source":"Clean","target":"Show-Info"}},{"data":{"id":"e186ebb1-d772-4ecd-921a-e9666e511f49","source":"Clean","target":"Print-AppVeyor-Environment-Variables"}},{"data":{"id":"Print-AppVeyor-Environment-Variables","source":null,"target":null}},{"data":{"id":"Show-Info","source":null,"target":null}},{"data":{"id":"Create-NuGet-Packages","source":null,"target":null}},{"data":{"id":"e4ab39be-e302-4665-8f41-0a48d325799d","source":"Create-NuGet-Packages","target":"Clean"}},{"data":{"id":"200944ea-51aa-4b32-8ccd-f3c7d8485c2c","source":"Create-NuGet-Packages","target":"Build"}},{"data":{"id":"Build","source":null,"target":null}},{"data":{"id":"b4d19157-78f6-45f1-9540-35afa52b7a1d","source":"Build","target":"Clean"}},{"data":{"id":"866c7216-4b5f-48f2-83f6-1829aef3b26d","source":"Build","target":"Restore"}},{"data":{"id":"Restore","source":null,"target":null}},{"data":{"id":"Clean","source":null,"target":null}},{"data":{"id":"52d1bb90-edfc-47ab-9936-b6fde71cbe1b","source":"Clean","target":"Show-Info"}},{"data":{"id":"e42c6269-b356-476b-a77a-58bfe8965e1e","source":"Clean","target":"Print-AppVeyor-Environment-Variables"}},{"data":{"id":"Print-AppVeyor-Environment-Variables","source":null,"target":null}},{"data":{"id":"Show-Info","source":null,"target":null}},{"data":{"id":"Clean","source":null,"target":null}},{"data":{"id":"d2f8fb6f-8f79-4650-9b16-09886d1706ab","source":"Clean","target":"Show-Info"}},{"data":{"id":"5802ff27-d930-4895-89c9-a3e8b57cd362","source":"Clean","target":"Print-AppVeyor-Environment-Variables"}},{"data":{"id":"Print-AppVeyor-Environment-Variables","source":null,"target":null}},{"data":{"id":"Show-Info","source":null,"target":null}},{"data":{"id":"Test","source":null,"target":null}},{"data":{"id":"bd24d0d0-eb69-4b2b-87ff-46d38068fa6a","source":"Test","target":"Build"}},{"data":{"id":"de06bd3c-df3b-43b7-b11b-65a7a210c66c","source":"Test","target":"Test-NUnit"}},{"data":{"id":"cee48667-e36e-4cad-9327-85ea152952d0","source":"Test","target":"Test-xUnit"}},{"data":{"id":"a3002b9b-2fda-46f4-a78b-a25d8d44f78b","source":"Test","target":"Test-MSTest"}},{"data":{"id":"2fe956ab-5d5f-468b-b824-0104ee61a046","source":"Test","target":"Test-VSTest"}},{"data":{"id":"937ae35b-841b-42e1-9db6-da280aba2883","source":"Test","target":"Test-Fixie"}},{"data":{"id":"Test-Fixie","source":null,"target":null}},{"data":{"id":"ee6805c1-46a0-4858-a605-f7b281b02ae6","source":"Test-Fixie","target":"Install-OpenCover"}},{"data":{"id":"Install-OpenCover","source":null,"target":null}},{"data":{"id":"7b426960-b53f-4733-b455-82b2d86c416a","source":"Install-OpenCover","target":"Install-ReportUnit"}},{"data":{"id":"Install-ReportUnit","source":null,"target":null}},{"data":{"id":"159fad20-03d4-42d9-919c-f778640ffb24","source":"Install-ReportUnit","target":"Install-ReportGenerator"}},{"data":{"id":"Install-ReportGenerator","source":null,"target":null}},{"data":{"id":"1e4209d9-306f-4072-824e-eb02254dc738","source":"Install-ReportGenerator","target":"Build"}},{"data":{"id":"Build","source":null,"target":null}},{"data":{"id":"b958c187-9226-4802-b4ce-caacaa224fb4","source":"Build","target":"Clean"}},{"data":{"id":"d65c206d-c8ca-49bd-97ea-61b449ab4f3c","source":"Build","target":"Restore"}},{"data":{"id":"Restore","source":null,"target":null}},{"data":{"id":"Clean","source":null,"target":null}},{"data":{"id":"f63d6d01-451a-40be-b7a3-f18987c66c7c","source":"Clean","target":"Show-Info"}},{"data":{"id":"cc81fc0a-2792-484c-96b8-79e49e230a1d","source":"Clean","target":"Print-AppVeyor-Environment-Variables"}},{"data":{"id":"Print-AppVeyor-Environment-Variables","source":null,"target":null}},{"data":{"id":"Show-Info","source":null,"target":null}},{"data":{"id":"Test-VSTest","source":null,"target":null}},{"data":{"id":"881a11c4-e673-4729-b2d3-d67af54c9d86","source":"Test-VSTest","target":"Install-OpenCover"}},{"data":{"id":"Install-OpenCover","source":null,"target":null}},{"data":{"id":"5d4a0283-d5d6-4bb7-b334-39a679242e1c","source":"Install-OpenCover","target":"Install-ReportUnit"}},{"data":{"id":"Install-ReportUnit","source":null,"target":null}},{"data":{"id":"10ea5c6e-b1b4-46e5-b7b8-dbcbf293cb5d","source":"Install-ReportUnit","target":"Install-ReportGenerator"}},{"data":{"id":"Install-ReportGenerator","source":null,"target":null}},{"data":{"id":"c4c26b14-b018-4ec7-9020-029a2ba2ec73","source":"Install-ReportGenerator","target":"Build"}},{"data":{"id":"Build","source":null,"target":null}},{"data":{"id":"fa31b4f0-c485-41d1-911c-c7ac49187de8","source":"Build","target":"Clean"}},{"data":{"id":"c463c385-f70e-4dd2-a083-82567263ff13","source":"Build","target":"Restore"}},{"data":{"id":"Restore","source":null,"target":null}},{"data":{"id":"Clean","source":null,"target":null}},{"data":{"id":"d83d4751-3ef1-4e03-a243-c07682230f81","source":"Clean","target":"Show-Info"}},{"data":{"id":"fa6a316f-c4c0-4cf5-adb7-3d5e3e9a980b","source":"Clean","target":"Print-AppVeyor-Environment-Variables"}},{"data":{"id":"Print-AppVeyor-Environment-Variables","source":null,"target":null}},{"data":{"id":"Show-Info","source":null,"target":null}},{"data":{"id":"Test-MSTest","source":null,"target":null}},{"data":{"id":"0b51ee13-6699-4330-9ec0-6e01b5f66540","source":"Test-MSTest","target":"Install-OpenCover"}},{"data":{"id":"Install-OpenCover","source":null,"target":null}},{"data":{"id":"b7dcac13-1537-466a-961f-27f86b83e6b7","source":"Install-OpenCover","target":"Install-ReportUnit"}},{"data":{"id":"Install-ReportUnit","source":null,"target":null}},{"data":{"id":"ca77f865-bb0f-4a75-98d8-1b961b676935","source":"Install-ReportUnit","target":"Install-ReportGenerator"}},{"data":{"id":"Install-ReportGenerator","source":null,"target":null}},{"data":{"id":"b776f41c-1b18-4a5d-bd11-7509ee2991f5","source":"Install-ReportGenerator","target":"Build"}},{"data":{"id":"Build","source":null,"target":null}},{"data":{"id":"43dd8f06-eb18-4938-b4cc-720da9fe8701","source":"Build","target":"Clean"}},{"data":{"id":"1bfd1c6a-55c7-469d-b355-22305acc7344","source":"Build","target":"Restore"}},{"data":{"id":"Restore","source":null,"target":null}},{"data":{"id":"Clean","source":null,"target":null}},{"data":{"id":"71e59eb6-f0ee-4ce8-a9a5-2685235d224b","source":"Clean","target":"Show-Info"}},{"data":{"id":"318ed2d4-54f6-4435-b839-109a1849a8ec","source":"Clean","target":"Print-AppVeyor-Environment-Variables"}},{"data":{"id":"Print-AppVeyor-Environment-Variables","source":null,"target":null}},{"data":{"id":"Show-Info","source":null,"target":null}},{"data":{"id":"Test-xUnit","source":null,"target":null}},{"data":{"id":"0dc3369a-1992-4430-af40-0eca1d6091bd","source":"Test-xUnit","target":"Install-OpenCover"}},{"data":{"id":"Install-OpenCover","source":null,"target":null}},{"data":{"id":"c94d8589-dab1-432d-947f-a6e75ecb3a38","source":"Install-OpenCover","target":"Install-ReportUnit"}},{"data":{"id":"Install-ReportUnit","source":null,"target":null}},{"data":{"id":"2dacb437-eedc-4766-8422-801dc877ff99","source":"Install-ReportUnit","target":"Install-ReportGenerator"}},{"data":{"id":"Install-ReportGenerator","source":null,"target":null}},{"data":{"id":"c5858e80-fa7f-49a6-a1bc-8c9459780e14","source":"Install-ReportGenerator","target":"Build"}},{"data":{"id":"Build","source":null,"target":null}},{"data":{"id":"17406a71-f8f7-4ead-889e-fb6873d4081b","source":"Build","target":"Clean"}},{"data":{"id":"14d9d4bb-ac6c-4ea9-969f-8bad2bf9f0b7","source":"Build","target":"Restore"}},{"data":{"id":"Restore","source":null,"target":null}},{"data":{"id":"Clean","source":null,"target":null}},{"data":{"id":"ad6e64ac-d1d7-4e60-97f6-70acd2ae7920","source":"Clean","target":"Show-Info"}},{"data":{"id":"674c5740-ccf7-4ac1-a442-bf03255acf50","source":"Clean","target":"Print-AppVeyor-Environment-Variables"}},{"data":{"id":"Print-AppVeyor-Environment-Variables","source":null,"target":null}},{"data":{"id":"Show-Info","source":null,"target":null}},{"data":{"id":"Test-NUnit","source":null,"target":null}},{"data":{"id":"32c38ef8-81ad-4625-941c-376992dfb95c","source":"Test-NUnit","target":"Install-OpenCover"}},{"data":{"id":"Install-OpenCover","source":null,"target":null}},{"data":{"id":"44f6c453-73c5-4895-92d1-393a8cdcdba5","source":"Install-OpenCover","target":"Install-ReportUnit"}},{"data":{"id":"Install-ReportUnit","source":null,"target":null}},{"data":{"id":"84ccc592-2db9-4504-9d7e-8c4631f7ded6","source":"Install-ReportUnit","target":"Install-ReportGenerator"}},{"data":{"id":"Install-ReportGenerator","source":null,"target":null}},{"data":{"id":"2691352a-a1cd-4355-9e19-a6c27a82c696","source":"Install-ReportGenerator","target":"Build"}},{"data":{"id":"Build","source":null,"target":null}},{"data":{"id":"c8880616-ff78-4a4f-af3c-d287d2829ceb","source":"Build","target":"Clean"}},{"data":{"id":"28569c6e-5cab-45b3-905d-143ca7650398","source":"Build","target":"Restore"}},{"data":{"id":"Restore","source":null,"target":null}},{"data":{"id":"Clean","source":null,"target":null}},{"data":{"id":"d141cd74-1862-4c8b-bf52-dae009c71843","source":"Clean","target":"Show-Info"}},{"data":{"id":"85154177-781a-4a65-9724-ee0d621182fb","source":"Clean","target":"Print-AppVeyor-Environment-Variables"}},{"data":{"id":"Print-AppVeyor-Environment-Variables","source":null,"target":null}},{"data":{"id":"Show-Info","source":null,"target":null}},{"data":{"id":"Build","source":null,"target":null}},{"data":{"id":"f1160d3a-1fe9-4de1-b89a-f9a0edc5e853","source":"Build","target":"Clean"}},{"data":{"id":"90fc6809-9656-4ff2-9ab4-c5f50f2b228f","source":"Build","target":"Restore"}},{"data":{"id":"Restore","source":null,"target":null}},{"data":{"id":"Clean","source":null,"target":null}},{"data":{"id":"3bda7630-e62d-4eee-bbbe-2bd53fa960ab","source":"Clean","target":"Show-Info"}},{"data":{"id":"d8c9ecad-0ba5-488e-a836-91c17ada83aa","source":"Clean","target":"Print-AppVeyor-Environment-Variables"}},{"data":{"id":"Print-AppVeyor-Environment-Variables","source":null,"target":null}},{"data":{"id":"Show-Info","source":null,"target":null}},{"data":{"id":"Analyze","source":null,"target":null}},{"data":{"id":"787072c5-b4fa-435d-b4ec-c05872a81a8a","source":"Analyze","target":"DupFinder"}},{"data":{"id":"d7e28151-ccf3-4ec4-8acc-747d01bee218","source":"Analyze","target":"InspectCode"}},{"data":{"id":"InspectCode","source":null,"target":null}},{"data":{"id":"6f17c859-1ac9-43cf-b170-2dbf8f52c8b8","source":"InspectCode","target":"Build"}},{"data":{"id":"Build","source":null,"target":null}},{"data":{"id":"a63497d2-8c4d-41e2-954b-cb7ecb5f2390","source":"Build","target":"Clean"}},{"data":{"id":"536643c5-237e-4173-bdae-6a7d180f69bd","source":"Build","target":"Restore"}},{"data":{"id":"Restore","source":null,"target":null}},{"data":{"id":"Clean","source":null,"target":null}},{"data":{"id":"c976e773-ec40-4d2d-bbdf-0687367658a2","source":"Clean","target":"Show-Info"}},{"data":{"id":"5b848e72-8ac5-47f6-b14d-93acf398fc72","source":"Clean","target":"Print-AppVeyor-Environment-Variables"}},{"data":{"id":"Print-AppVeyor-Environment-Variables","source":null,"target":null}},{"data":{"id":"Show-Info","source":null,"target":null}},{"data":{"id":"DupFinder","source":null,"target":null}},{"data":{"id":"4bcc4fd3-dd0a-4268-a322-158d7fb7b602","source":"DupFinder","target":"Build"}},{"data":{"id":"Build","source":null,"target":null}},{"data":{"id":"7ee9490d-64a0-46c2-8ae9-c437ae64e608","source":"Build","target":"Clean"}},{"data":{"id":"61e570d6-11a0-4743-a2c5-d3734dea670f","source":"Build","target":"Restore"}},{"data":{"id":"Restore","source":null,"target":null}},{"data":{"id":"Clean","source":null,"target":null}},{"data":{"id":"e1b83709-9a9a-45bc-9149-bd55438b9272","source":"Clean","target":"Show-Info"}},{"data":{"id":"f06064da-de48-4392-8ad7-10c608ecf841","source":"Clean","target":"Print-AppVeyor-Environment-Variables"}},{"data":{"id":"Print-AppVeyor-Environment-Variables","source":null,"target":null}},{"data":{"id":"Show-Info","source":null,"target":null}},{"data":{"id":"Export-Release-Notes","source":null,"target":null}},{"data":{"id":"Upload-AppVeyor-Artifacts","source":null,"target":null}},{"data":{"id":"bdfc87ad-2760-426b-97a5-a290460f8756","source":"Upload-AppVeyor-Artifacts","target":"Package"}},{"data":{"id":"Package","source":null,"target":null}},{"data":{"id":"b2cfb115-62d8-40a8-a506-d826979fd675","source":"Package","target":"Export-Release-Notes"}},{"data":{"id":"a16a7cc3-1f20-4b44-8941-480edf19ad64","source":"Package","target":"Analyze"}},{"data":{"id":"a6c6323c-a90d-465d-b488-7e02c3d89729","source":"Package","target":"Test"}},{"data":{"id":"02d27011-a149-42b3-82b9-762334274ca2","source":"Package","target":"Create-NuGet-Packages"}},{"data":{"id":"5c19b4ee-168e-4cbb-9b84-6dbfc678378d","source":"Package","target":"Create-Chocolatey-Packages"}},{"data":{"id":"Create-Chocolatey-Packages","source":null,"target":null}},{"data":{"id":"749d1747-e2ad-401f-b424-0621f686dbf8","source":"Create-Chocolatey-Packages","target":"Clean"}},{"data":{"id":"17b0c3b7-7e9b-41cd-836a-4bc365f7d48e","source":"Create-Chocolatey-Packages","target":"Build"}},{"data":{"id":"Build","source":null,"target":null}},{"data":{"id":"a713733c-a600-4483-bddc-8088529b8659","source":"Build","target":"Clean"}},{"data":{"id":"eca34578-5f61-4f97-a998-88f67c12917e","source":"Build","target":"Restore"}},{"data":{"id":"Restore","source":null,"target":null}},{"data":{"id":"Clean","source":null,"target":null}},{"data":{"id":"c6d438fc-8fd9-4b31-a240-f11c1046cdf9","source":"Clean","target":"Show-Info"}},{"data":{"id":"95469891-899f-48de-a621-44c714a844bb","source":"Clean","target":"Print-AppVeyor-Environment-Variables"}},{"data":{"id":"Print-AppVeyor-Environment-Variables","source":null,"target":null}},{"data":{"id":"Show-Info","source":null,"target":null}},{"data":{"id":"Clean","source":null,"target":null}},{"data":{"id":"65b9f300-86bf-4d1e-ac45-853a561a72d2","source":"Clean","target":"Show-Info"}},{"data":{"id":"ce26e6b5-9ba3-454c-8a4f-b0e28e4d7e52","source":"Clean","target":"Print-AppVeyor-Environment-Variables"}},{"data":{"id":"Print-AppVeyor-Environment-Variables","source":null,"target":null}},{"data":{"id":"Show-Info","source":null,"target":null}},{"data":{"id":"Create-NuGet-Packages","source":null,"target":null}},{"data":{"id":"399cd9bf-2545-4ce5-b323-b5b38732cc95","source":"Create-NuGet-Packages","target":"Clean"}},{"data":{"id":"39d7cab6-709e-4b59-a0b7-153f8321a334","source":"Create-NuGet-Packages","target":"Build"}},{"data":{"id":"Build","source":null,"target":null}},{"data":{"id":"d150f5e1-41c3-4bd3-83e9-a4c4e7847952","source":"Build","target":"Clean"}},{"data":{"id":"24e26c54-ab61-4d81-8ee3-3a1441f96262","source":"Build","target":"Restore"}},{"data":{"id":"Restore","source":null,"target":null}},{"data":{"id":"Clean","source":null,"target":null}},{"data":{"id":"ad5e6f01-6d62-4179-9366-c66df82c4abd","source":"Clean","target":"Show-Info"}},{"data":{"id":"51c83ff2-e784-4bc7-bd87-342496bf2778","source":"Clean","target":"Print-AppVeyor-Environment-Variables"}},{"data":{"id":"Print-AppVeyor-Environment-Variables","source":null,"target":null}},{"data":{"id":"Show-Info","source":null,"target":null}},{"data":{"id":"Clean","source":null,"target":null}},{"data":{"id":"50dd203b-930e-47a6-a138-056abe6beee3","source":"Clean","target":"Show-Info"}},{"data":{"id":"d8a66cfe-bd6e-4644-9186-9307b653137d","source":"Clean","target":"Print-AppVeyor-Environment-Variables"}},{"data":{"id":"Print-AppVeyor-Environment-Variables","source":null,"target":null}},{"data":{"id":"Show-Info","source":null,"target":null}},{"data":{"id":"Test","source":null,"target":null}},{"data":{"id":"d1cfce40-345e-48a0-ac66-15709af35f0f","source":"Test","target":"Build"}},{"data":{"id":"5c9a592f-b175-43bc-b454-25236bc53a6d","source":"Test","target":"Test-NUnit"}},{"data":{"id":"87f46372-2faf-4f56-ade7-f006993a35fb","source":"Test","target":"Test-xUnit"}},{"data":{"id":"d0b89609-b63c-401a-87a0-e39a42aa172f","source":"Test","target":"Test-MSTest"}},{"data":{"id":"0504d7ea-ffb2-442e-b6f4-d558bdc6eeb7","source":"Test","target":"Test-VSTest"}},{"data":{"id":"d3b779b0-8c8d-4cfa-8475-edfb673634d9","source":"Test","target":"Test-Fixie"}},{"data":{"id":"Test-Fixie","source":null,"target":null}},{"data":{"id":"674cca0a-e5b5-4f63-bf37-a7ffbf29cf1f","source":"Test-Fixie","target":"Install-OpenCover"}},{"data":{"id":"Install-OpenCover","source":null,"target":null}},{"data":{"id":"d48eeafd-0b60-45c3-9394-0b8c77a88b84","source":"Install-OpenCover","target":"Install-ReportUnit"}},{"data":{"id":"Install-ReportUnit","source":null,"target":null}},{"data":{"id":"029a86ba-7c20-4cc3-a0c8-a0975f1ec288","source":"Install-ReportUnit","target":"Install-ReportGenerator"}},{"data":{"id":"Install-ReportGenerator","source":null,"target":null}},{"data":{"id":"bb7e6d20-fd8e-4103-8dec-71383e2ceaca","source":"Install-ReportGenerator","target":"Build"}},{"data":{"id":"Build","source":null,"target":null}},{"data":{"id":"8247e7c6-4369-44f4-a587-c00eff6f67be","source":"Build","target":"Clean"}},{"data":{"id":"bc886851-0735-4f5e-b0be-b05658dd731c","source":"Build","target":"Restore"}},{"data":{"id":"Restore","source":null,"target":null}},{"data":{"id":"Clean","source":null,"target":null}},{"data":{"id":"fe3e6458-0b89-48d7-9735-0754f558c6b9","source":"Clean","target":"Show-Info"}},{"data":{"id":"cc60726b-a842-4169-a11d-a5235e6ec048","source":"Clean","target":"Print-AppVeyor-Environment-Variables"}},{"data":{"id":"Print-AppVeyor-Environment-Variables","source":null,"target":null}},{"data":{"id":"Show-Info","source":null,"target":null}},{"data":{"id":"Test-VSTest","source":null,"target":null}},{"data":{"id":"38acc759-d696-447d-8ebc-0ac1297ebff7","source":"Test-VSTest","target":"Install-OpenCover"}},{"data":{"id":"Install-OpenCover","source":null,"target":null}},{"data":{"id":"c930dcd9-c8d4-45f7-9d90-9c03d4b2fe16","source":"Install-OpenCover","target":"Install-ReportUnit"}},{"data":{"id":"Install-ReportUnit","source":null,"target":null}},{"data":{"id":"f2839490-f692-4fd8-8455-0b11c10bbf0e","source":"Install-ReportUnit","target":"Install-ReportGenerator"}},{"data":{"id":"Install-ReportGenerator","source":null,"target":null}},{"data":{"id":"c05a6ea6-ddc0-4d56-b0bb-c3e4229b6165","source":"Install-ReportGenerator","target":"Build"}},{"data":{"id":"Build","source":null,"target":null}},{"data":{"id":"d3b964f5-33d9-4438-869b-7b9f074ddc89","source":"Build","target":"Clean"}},{"data":{"id":"c701c52c-9ebc-4886-a0b2-44be4fbd46be","source":"Build","target":"Restore"}},{"data":{"id":"Restore","source":null,"target":null}},{"data":{"id":"Clean","source":null,"target":null}},{"data":{"id":"2fbff202-0abb-4fd2-bd3b-f971143c34c7","source":"Clean","target":"Show-Info"}},{"data":{"id":"48261340-c3c6-46cd-8c1e-4fb8961b3ae0","source":"Clean","target":"Print-AppVeyor-Environment-Variables"}},{"data":{"id":"Print-AppVeyor-Environment-Variables","source":null,"target":null}},{"data":{"id":"Show-Info","source":null,"target":null}},{"data":{"id":"Test-MSTest","source":null,"target":null}},{"data":{"id":"1f70914b-ba3d-405c-b4bf-50ba66430b95","source":"Test-MSTest","target":"Install-OpenCover"}},{"data":{"id":"Install-OpenCover","source":null,"target":null}},{"data":{"id":"7b21e834-6df1-45d4-92fd-5c7b41f11cc7","source":"Install-OpenCover","target":"Install-ReportUnit"}},{"data":{"id":"Install-ReportUnit","source":null,"target":null}},{"data":{"id":"f8bc5055-f9b8-4b81-9460-0e29107b4c56","source":"Install-ReportUnit","target":"Install-ReportGenerator"}},{"data":{"id":"Install-ReportGenerator","source":null,"target":null}},{"data":{"id":"9ea964b9-bbe1-42e7-b66a-99c2c874a262","source":"Install-ReportGenerator","target":"Build"}},{"data":{"id":"Build","source":null,"target":null}},{"data":{"id":"eb1f7a33-4698-4b75-ad01-5ebdef1be57a","source":"Build","target":"Clean"}},{"data":{"id":"6ed09316-0e9b-4b14-b407-a4febcbb5854","source":"Build","target":"Restore"}},{"data":{"id":"Restore","source":null,"target":null}},{"data":{"id":"Clean","source":null,"target":null}},{"data":{"id":"1b667621-62c0-468e-a31f-98db476ef957","source":"Clean","target":"Show-Info"}},{"data":{"id":"20630ddf-f689-469c-88e1-3085983f29b6","source":"Clean","target":"Print-AppVeyor-Environment-Variables"}},{"data":{"id":"Print-AppVeyor-Environment-Variables","source":null,"target":null}},{"data":{"id":"Show-Info","source":null,"target":null}},{"data":{"id":"Test-xUnit","source":null,"target":null}},{"data":{"id":"9ef1052b-febe-423d-8882-24f3494e4712","source":"Test-xUnit","target":"Install-OpenCover"}},{"data":{"id":"Install-OpenCover","source":null,"target":null}},{"data":{"id":"9084062c-6cae-4216-a4ac-fb93c8c10788","source":"Install-OpenCover","target":"Install-ReportUnit"}},{"data":{"id":"Install-ReportUnit","source":null,"target":null}},{"data":{"id":"4ac200ad-7b04-4221-8036-07b4e59a5a70","source":"Install-ReportUnit","target":"Install-ReportGenerator"}},{"data":{"id":"Install-ReportGenerator","source":null,"target":null}},{"data":{"id":"67caf239-4870-4984-b4d6-ac20ba1d4d92","source":"Install-ReportGenerator","target":"Build"}},{"data":{"id":"Build","source":null,"target":null}},{"data":{"id":"2e7fe889-d990-45f1-9eae-4f5975ce9f2d","source":"Build","target":"Clean"}},{"data":{"id":"5eb8a4da-8efa-4512-a0fe-456df06a59c6","source":"Build","target":"Restore"}},{"data":{"id":"Restore","source":null,"target":null}},{"data":{"id":"Clean","source":null,"target":null}},{"data":{"id":"9547d544-b922-4c99-a68f-c3e01a14f659","source":"Clean","target":"Show-Info"}},{"data":{"id":"14d55b2a-8393-4c74-9315-6b8d4c856474","source":"Clean","target":"Print-AppVeyor-Environment-Variables"}},{"data":{"id":"Print-AppVeyor-Environment-Variables","source":null,"target":null}},{"data":{"id":"Show-Info","source":null,"target":null}},{"data":{"id":"Test-NUnit","source":null,"target":null}},{"data":{"id":"d8bf062c-1554-43c0-aa4a-502073e00847","source":"Test-NUnit","target":"Install-OpenCover"}},{"data":{"id":"Install-OpenCover","source":null,"target":null}},{"data":{"id":"cb4136f9-c913-407c-ad3a-f16e565fac12","source":"Install-OpenCover","target":"Install-ReportUnit"}},{"data":{"id":"Install-ReportUnit","source":null,"target":null}},{"data":{"id":"3f423d30-b8e7-4b9c-8ffb-7ec77676a2b8","source":"Install-ReportUnit","target":"Install-ReportGenerator"}},{"data":{"id":"Install-ReportGenerator","source":null,"target":null}},{"data":{"id":"e30986f2-33be-4df0-933d-1d6161185852","source":"Install-ReportGenerator","target":"Build"}},{"data":{"id":"Build","source":null,"target":null}},{"data":{"id":"702e4eb0-dc49-4c51-9ccc-79c8f16bca20","source":"Build","target":"Clean"}},{"data":{"id":"51b5d15f-030d-462d-b8b9-6b6c15babd1d","source":"Build","target":"Restore"}},{"data":{"id":"Restore","source":null,"target":null}},{"data":{"id":"Clean","source":null,"target":null}},{"data":{"id":"0e046303-7c61-4aa2-812a-9a91d77e16bc","source":"Clean","target":"Show-Info"}},{"data":{"id":"d6472e53-221e-4fbe-aa28-0465d38b8de9","source":"Clean","target":"Print-AppVeyor-Environment-Variables"}},{"data":{"id":"Print-AppVeyor-Environment-Variables","source":null,"target":null}},{"data":{"id":"Show-Info","source":null,"target":null}},{"data":{"id":"Build","source":null,"target":null}},{"data":{"id":"7918549b-cf23-4324-b15a-13c89ad1346c","source":"Build","target":"Clean"}},{"data":{"id":"94905a71-8c5d-4df4-814f-26a87551e80d","source":"Build","target":"Restore"}},{"data":{"id":"Restore","source":null,"target":null}},{"data":{"id":"Clean","source":null,"target":null}},{"data":{"id":"c87bbc24-1a20-44d4-8852-3fe9bbe96474","source":"Clean","target":"Show-Info"}},{"data":{"id":"bb7524eb-d27f-4cf6-8269-3f2b044cce57","source":"Clean","target":"Print-AppVeyor-Environment-Variables"}},{"data":{"id":"Print-AppVeyor-Environment-Variables","source":null,"target":null}},{"data":{"id":"Show-Info","source":null,"target":null}},{"data":{"id":"Analyze","source":null,"target":null}},{"data":{"id":"1c1a96b1-a427-46d0-a33e-154a37ab40f2","source":"Analyze","target":"DupFinder"}},{"data":{"id":"4c088c8d-6b85-4d6f-a9ee-8fc68b5d462e","source":"Analyze","target":"InspectCode"}},{"data":{"id":"InspectCode","source":null,"target":null}},{"data":{"id":"38b2f42e-f803-4e03-a111-cf3f0b4e61e9","source":"InspectCode","target":"Build"}},{"data":{"id":"Build","source":null,"target":null}},{"data":{"id":"154c8b1b-34f6-4f62-9fba-a6571af7e4ea","source":"Build","target":"Clean"}},{"data":{"id":"4d2c8351-c083-4e79-b0fa-2623d2f95563","source":"Build","target":"Restore"}},{"data":{"id":"Restore","source":null,"target":null}},{"data":{"id":"Clean","source":null,"target":null}},{"data":{"id":"393a8fb4-2cce-4ec5-8b8c-3ea7afd64cc4","source":"Clean","target":"Show-Info"}},{"data":{"id":"d7ea64ef-df66-44b5-bb17-9c684b5087ad","source":"Clean","target":"Print-AppVeyor-Environment-Variables"}},{"data":{"id":"Print-AppVeyor-Environment-Variables","source":null,"target":null}},{"data":{"id":"Show-Info","source":null,"target":null}},{"data":{"id":"DupFinder","source":null,"target":null}},{"data":{"id":"56b7128a-9115-4a1e-8d19-1cc345596fae","source":"DupFinder","target":"Build"}},{"data":{"id":"Build","source":null,"target":null}},{"data":{"id":"a6ca5833-2534-4c5e-92da-b77a97f683f5","source":"Build","target":"Clean"}},{"data":{"id":"e11645af-5108-4b69-8f0a-d4ad4e556504","source":"Build","target":"Restore"}},{"data":{"id":"Restore","source":null,"target":null}},{"data":{"id":"Clean","source":null,"target":null}},{"data":{"id":"cd09aecf-c811-4119-b5e3-60755523911b","source":"Clean","target":"Show-Info"}},{"data":{"id":"1914025c-eca0-42b6-b30b-773b6fe6dacb","source":"Clean","target":"Print-AppVeyor-Environment-Variables"}},{"data":{"id":"Print-AppVeyor-Environment-Variables","source":null,"target":null}},{"data":{"id":"Show-Info","source":null,"target":null}},{"data":{"id":"Export-Release-Notes","source":null,"target":null}}]